{
"meta":{"test_sets":[],"test_metrics":[],"learn_metrics":[{"best_value":"Min","name":"Logloss"}],"launch_mode":"Train","parameters":"","iteration_count":1000,"learn_sets":["learn"],"name":"experiment"},
"iterations":[
{"learn":[0.6714049719],"iteration":0,"passed_time":0.01391045581,"remaining_time":13.89654535},
{"learn":[0.6516673707],"iteration":1,"passed_time":0.02360364247,"remaining_time":11.77821759},
{"learn":[0.6337930001],"iteration":2,"passed_time":0.03530312025,"remaining_time":11.73240363},
{"learn":[0.6168789731],"iteration":3,"passed_time":0.04355067348,"remaining_time":10.8441177},
{"learn":[0.6025180767],"iteration":4,"passed_time":0.05282190944,"remaining_time":10.51155998},
{"learn":[0.5883146526],"iteration":5,"passed_time":0.06049555495,"remaining_time":10.02209694},
{"learn":[0.5756996683],"iteration":6,"passed_time":0.0672377592,"remaining_time":9.538156412},
{"learn":[0.5643468518],"iteration":7,"passed_time":0.07656855595,"remaining_time":9.494500938},
{"learn":[0.5536666853],"iteration":8,"passed_time":0.08298424909,"remaining_time":9.137487872},
{"learn":[0.5441832581],"iteration":9,"passed_time":0.09003374029,"remaining_time":8.913340288},
{"learn":[0.5355204664],"iteration":10,"passed_time":0.09781280633,"remaining_time":8.794260496},
{"learn":[0.5275327383],"iteration":11,"passed_time":0.1074435909,"remaining_time":8.846188982},
{"learn":[0.5198082562],"iteration":12,"passed_time":0.1152504319,"remaining_time":8.750167407},
{"learn":[0.5127545079],"iteration":13,"passed_time":0.1218198854,"remaining_time":8.579600499},
{"learn":[0.5065014955],"iteration":14,"passed_time":0.1290794763,"remaining_time":8.476218946},
{"learn":[0.5005334618],"iteration":15,"passed_time":0.1358469526,"remaining_time":8.354587586},
{"learn":[0.4948806393],"iteration":16,"passed_time":0.143642448,"remaining_time":8.305913316},
{"learn":[0.4900257539],"iteration":17,"passed_time":0.1507796983,"remaining_time":8.22587021},
{"learn":[0.4853295849],"iteration":18,"passed_time":0.1584493391,"remaining_time":8.180989559},
{"learn":[0.4812787824],"iteration":19,"passed_time":0.1658593066,"remaining_time":8.127106023},
{"learn":[0.4772966132],"iteration":20,"passed_time":0.1731565472,"remaining_time":8.07239332},
{"learn":[0.4737715379],"iteration":21,"passed_time":0.1801255363,"remaining_time":8.007398842},
{"learn":[0.4705685912],"iteration":22,"passed_time":0.1865745063,"remaining_time":7.925360549},
{"learn":[0.4675278294],"iteration":23,"passed_time":0.1938862658,"remaining_time":7.884708144},
{"learn":[0.4647262503],"iteration":24,"passed_time":0.2004284828,"remaining_time":7.816710828},
{"learn":[0.4620312884],"iteration":25,"passed_time":0.2078434586,"remaining_time":7.786135718},
{"learn":[0.4595550946],"iteration":26,"passed_time":0.2146007258,"remaining_time":7.733574305},
{"learn":[0.4573145737],"iteration":27,"passed_time":0.2212140445,"remaining_time":7.679287543},
{"learn":[0.4553136993],"iteration":28,"passed_time":0.2284884414,"remaining_time":7.650423331},
{"learn":[0.4532497144],"iteration":29,"passed_time":0.2350049212,"remaining_time":7.598492453},
{"learn":[0.4514006857],"iteration":30,"passed_time":0.2430113715,"remaining_time":7.596065129},
{"learn":[0.4498803491],"iteration":31,"passed_time":0.24989475,"remaining_time":7.559316187},
{"learn":[0.4483614671],"iteration":32,"passed_time":0.2574253413,"remaining_time":7.543342578},
{"learn":[0.4468706488],"iteration":33,"passed_time":0.2639794239,"remaining_time":7.50012128},
{"learn":[0.445386403],"iteration":34,"passed_time":0.2707536116,"remaining_time":7.465063863},
{"learn":[0.4441507319],"iteration":35,"passed_time":0.277912361,"remaining_time":7.441875444},
{"learn":[0.4429132637],"iteration":36,"passed_time":0.2844985745,"remaining_time":7.404652089},
{"learn":[0.4417418471],"iteration":37,"passed_time":0.2917741542,"remaining_time":7.386493062},
{"learn":[0.4405433502],"iteration":38,"passed_time":0.2983139235,"remaining_time":7.350761038},
{"learn":[0.4395825832],"iteration":39,"passed_time":0.3059211409,"remaining_time":7.342107381},
{"learn":[0.4387336484],"iteration":40,"passed_time":0.3125937252,"remaining_time":7.311643475},
{"learn":[0.4377911778],"iteration":41,"passed_time":0.3191700088,"remaining_time":7.280115915},
{"learn":[0.4369089206],"iteration":42,"passed_time":0.3265682137,"remaining_time":7.268041407},
{"learn":[0.43612322],"iteration":43,"passed_time":0.3342494635,"remaining_time":7.262329252},
{"learn":[0.4353690378],"iteration":44,"passed_time":0.3445202511,"remaining_time":7.311485329},
{"learn":[0.4347947818],"iteration":45,"passed_time":0.3520483403,"remaining_time":7.30117645},
{"learn":[0.4341042911],"iteration":46,"passed_time":0.3598662736,"remaining_time":7.296862953},
{"learn":[0.4333776879],"iteration":47,"passed_time":0.3664997879,"remaining_time":7.268912459},
{"learn":[0.4327840302],"iteration":48,"passed_time":0.3742266227,"remaining_time":7.263051392},
{"learn":[0.432234029],"iteration":49,"passed_time":0.380867564,"remaining_time":7.236483716},
{"learn":[0.4316577892],"iteration":50,"passed_time":0.3880730042,"remaining_time":7.221201588},
{"learn":[0.4311484393],"iteration":51,"passed_time":0.3964705992,"remaining_time":7.227964001},
{"learn":[0.4305544454],"iteration":52,"passed_time":0.4038971741,"remaining_time":7.216804224},
{"learn":[0.4300570397],"iteration":53,"passed_time":0.4107885453,"remaining_time":7.196406738},
{"learn":[0.4296029743],"iteration":54,"passed_time":0.4174469539,"remaining_time":7.172497663},
{"learn":[0.4292057342],"iteration":55,"passed_time":0.4249130018,"remaining_time":7.162819174},
{"learn":[0.4287182807],"iteration":56,"passed_time":0.4314405527,"remaining_time":7.13769195},
{"learn":[0.4283068331],"iteration":57,"passed_time":0.4389541121,"remaining_time":7.129220235},
{"learn":[0.428028721],"iteration":58,"passed_time":0.4456658548,"remaining_time":7.107992701},
{"learn":[0.4276925623],"iteration":59,"passed_time":0.4524526134,"remaining_time":7.088424276},
{"learn":[0.4273284774],"iteration":60,"passed_time":0.460806644,"remaining_time":7.093400634},
{"learn":[0.4269273624],"iteration":61,"passed_time":0.4678304975,"remaining_time":7.077822688},
{"learn":[0.4265864621],"iteration":62,"passed_time":0.4754479195,"remaining_time":7.071344453},
{"learn":[0.4262739606],"iteration":63,"passed_time":0.481842709,"remaining_time":7.046949619},
{"learn":[0.4260059491],"iteration":64,"passed_time":0.4893485463,"remaining_time":7.039090627},
{"learn":[0.4256376204],"iteration":65,"passed_time":0.4959241411,"remaining_time":7.018077996},
{"learn":[0.4253777747],"iteration":66,"passed_time":0.5036535507,"remaining_time":7.013563623},
{"learn":[0.4251025343],"iteration":67,"passed_time":0.510274298,"remaining_time":6.993759496},
{"learn":[0.4248288657],"iteration":68,"passed_time":0.5170899004,"remaining_time":6.976966627},
{"learn":[0.42449759],"iteration":69,"passed_time":0.5247242837,"remaining_time":6.971336912},
{"learn":[0.4242715438],"iteration":70,"passed_time":0.5311866452,"remaining_time":6.9503154},
{"learn":[0.4240633162],"iteration":71,"passed_time":0.5384792652,"remaining_time":6.940399419},
{"learn":[0.4237961166],"iteration":72,"passed_time":0.5449175515,"remaining_time":6.919706441},
{"learn":[0.4235592739],"iteration":73,"passed_time":0.5527468485,"remaining_time":6.916805158},
{"learn":[0.4233669416],"iteration":74,"passed_time":0.5602073533,"remaining_time":6.909224024},
{"learn":[0.4230642827],"iteration":75,"passed_time":0.5678495514,"remaining_time":6.903855072},
{"learn":[0.4228459771],"iteration":76,"passed_time":0.574407943,"remaining_time":6.885435473},
{"learn":[0.4226216385],"iteration":77,"passed_time":0.5809872584,"remaining_time":6.867567336},
{"learn":[0.4224315933],"iteration":78,"passed_time":0.5880601986,"remaining_time":6.855739784},
{"learn":[0.4222111503],"iteration":79,"passed_time":0.5950642206,"remaining_time":6.843238537},
{"learn":[0.4219434684],"iteration":80,"passed_time":0.602570197,"remaining_time":6.836568038},
{"learn":[0.4216596827],"iteration":81,"passed_time":0.6092619742,"remaining_time":6.820762102},
{"learn":[0.4214905231],"iteration":82,"passed_time":0.6160093243,"remaining_time":6.805789764},
{"learn":[0.4212106241],"iteration":83,"passed_time":0.6229263092,"remaining_time":6.792863086},
{"learn":[0.4210391454],"iteration":84,"passed_time":0.6297687781,"remaining_time":6.77927567},
{"learn":[0.4208953437],"iteration":85,"passed_time":0.6371462566,"remaining_time":6.771531146},
{"learn":[0.4207478392],"iteration":86,"passed_time":0.643786394,"remaining_time":6.756057216},
{"learn":[0.4205415867],"iteration":87,"passed_time":0.6507186151,"remaining_time":6.743811102},
{"learn":[0.4203822478],"iteration":88,"passed_time":0.6574704936,"remaining_time":6.729838423},
{"learn":[0.4202020308],"iteration":89,"passed_time":0.6641654769,"remaining_time":6.715450934},
{"learn":[0.4200159769],"iteration":90,"passed_time":0.6724715702,"remaining_time":6.717325905},
{"learn":[0.4198936763],"iteration":91,"passed_time":0.6792530687,"remaining_time":6.703932461},
{"learn":[0.4196835341],"iteration":92,"passed_time":0.6877933555,"remaining_time":6.707834123},
{"learn":[0.4195165909],"iteration":93,"passed_time":0.6945077074,"remaining_time":6.693872158},
{"learn":[0.4193129035],"iteration":94,"passed_time":0.7015265638,"remaining_time":6.682963581},
{"learn":[0.4191906811],"iteration":95,"passed_time":0.7083073274,"remaining_time":6.669894},
{"learn":[0.4190445033],"iteration":96,"passed_time":0.7154832722,"remaining_time":6.660632936},
{"learn":[0.4189053742],"iteration":97,"passed_time":0.7231282074,"remaining_time":6.655731052},
{"learn":[0.4188095389],"iteration":98,"passed_time":0.7295007041,"remaining_time":6.639193277},
{"learn":[0.4185861804],"iteration":99,"passed_time":0.7365943784,"remaining_time":6.629349406},
{"learn":[0.418488903],"iteration":100,"passed_time":0.7429133867,"remaining_time":6.612664699},
{"learn":[0.4183516214],"iteration":101,"passed_time":0.7503308807,"remaining_time":6.605854224},
{"learn":[0.4181894485],"iteration":102,"passed_time":0.7570981814,"remaining_time":6.593369599},
{"learn":[0.4180357953],"iteration":103,"passed_time":0.7645339718,"remaining_time":6.586754219},
{"learn":[0.417833156],"iteration":104,"passed_time":0.7721362378,"remaining_time":6.581542217},
{"learn":[0.4176950183],"iteration":105,"passed_time":0.7794863182,"remaining_time":6.574158193},
{"learn":[0.4174921444],"iteration":106,"passed_time":0.7863014772,"remaining_time":6.562310459},
{"learn":[0.4173297248],"iteration":107,"passed_time":0.792932405,"remaining_time":6.549034308},
{"learn":[0.4172344242],"iteration":108,"passed_time":0.8052148746,"remaining_time":6.582077553},
{"learn":[0.4170663943],"iteration":109,"passed_time":0.8125258391,"remaining_time":6.574072698},
{"learn":[0.4169719842],"iteration":110,"passed_time":0.8191225913,"remaining_time":6.560360213},
{"learn":[0.4168128628],"iteration":111,"passed_time":0.8257908124,"remaining_time":6.547341441},
{"learn":[0.416697047],"iteration":112,"passed_time":0.8331303289,"remaining_time":6.53970444},
{"learn":[0.4165731075],"iteration":113,"passed_time":0.8396117683,"remaining_time":6.525403743},
{"learn":[0.4163889637],"iteration":114,"passed_time":0.8473996983,"remaining_time":6.52129333},
{"learn":[0.4162825849],"iteration":115,"passed_time":0.8541216556,"remaining_time":6.508996065},
{"learn":[0.4161330255],"iteration":116,"passed_time":0.8616439331,"remaining_time":6.502834127},
{"learn":[0.4159490299],"iteration":117,"passed_time":0.8692717594,"remaining_time":6.497438066},
{"learn":[0.4157777288],"iteration":118,"passed_time":0.8758053866,"remaining_time":6.483903744},
{"learn":[0.4156637349],"iteration":119,"passed_time":0.8827722712,"remaining_time":6.473663322},
{"learn":[0.4155312433],"iteration":120,"passed_time":0.8893696597,"remaining_time":6.460792817},
{"learn":[0.4154484197],"iteration":121,"passed_time":0.8965447754,"remaining_time":6.452182892},
{"learn":[0.4153919715],"iteration":122,"passed_time":0.9030862587,"remaining_time":6.439078446},
{"learn":[0.4152389179],"iteration":123,"passed_time":0.909913424,"remaining_time":6.42809806},
{"learn":[0.4150950528],"iteration":124,"passed_time":0.9168139307,"remaining_time":6.417697515},
{"learn":[0.4149627098],"iteration":125,"passed_time":0.9236562039,"remaining_time":6.406948589},
{"learn":[0.4148366261],"iteration":126,"passed_time":0.9311186833,"remaining_time":6.400524492},
{"learn":[0.4147172035],"iteration":127,"passed_time":0.9387518995,"remaining_time":6.395247315},
{"learn":[0.4145847647],"iteration":128,"passed_time":0.9466704511,"remaining_time":6.391860178},
{"learn":[0.4144331433],"iteration":129,"passed_time":0.953781618,"remaining_time":6.383000059},
{"learn":[0.4143055959],"iteration":130,"passed_time":0.9611939854,"remaining_time":6.376164682},
{"learn":[0.4142074533],"iteration":131,"passed_time":0.9680663907,"remaining_time":6.365769902},
{"learn":[0.4140645806],"iteration":132,"passed_time":0.9748215643,"remaining_time":6.354663882},
{"learn":[0.4140159807],"iteration":133,"passed_time":0.9822876708,"remaining_time":6.348217335},
{"learn":[0.4139067375],"iteration":134,"passed_time":0.988528216,"remaining_time":6.333903014},
{"learn":[0.4138174265],"iteration":135,"passed_time":0.9957489706,"remaining_time":6.325934637},
{"learn":[0.4137250574],"iteration":136,"passed_time":1.002109659,"remaining_time":6.312559385},
{"learn":[0.4136280788],"iteration":137,"passed_time":1.009405227,"remaining_time":6.305125406},
{"learn":[0.4134758147],"iteration":138,"passed_time":1.018677241,"remaining_time":6.309936002},
{"learn":[0.4133645088],"iteration":139,"passed_time":1.027378111,"remaining_time":6.311036966},
{"learn":[0.4132668241],"iteration":140,"passed_time":1.033938635,"remaining_time":6.298959485},
{"learn":[0.4131138848],"iteration":141,"passed_time":1.041231069,"remaining_time":6.291382094},
{"learn":[0.4130562421],"iteration":142,"passed_time":1.048246675,"remaining_time":6.282149651},
{"learn":[0.4129290265],"iteration":143,"passed_time":1.054794533,"remaining_time":6.270167503},
{"learn":[0.4127839118],"iteration":144,"passed_time":1.062848876,"remaining_time":6.26714337},
{"learn":[0.4127232561],"iteration":145,"passed_time":1.069097618,"remaining_time":6.253488809},
{"learn":[0.4126276059],"iteration":146,"passed_time":1.076930437,"remaining_time":6.249126959},
{"learn":[0.4125693572],"iteration":147,"passed_time":1.083786798,"remaining_time":6.23909697},
{"learn":[0.4124712832],"iteration":148,"passed_time":1.090996391,"remaining_time":6.231127036},
{"learn":[0.4123381725],"iteration":149,"passed_time":1.097737039,"remaining_time":6.220509889},
{"learn":[0.4121797003],"iteration":150,"passed_time":1.104453722,"remaining_time":6.209809338},
{"learn":[0.4120335347],"iteration":151,"passed_time":1.112569676,"remaining_time":6.206967665},
{"learn":[0.4119562633],"iteration":152,"passed_time":1.118936682,"remaining_time":6.194374965},
{"learn":[0.411869231],"iteration":153,"passed_time":1.126366137,"remaining_time":6.187699685},
{"learn":[0.4118258568],"iteration":154,"passed_time":1.132602961,"remaining_time":6.174512914},
{"learn":[0.4117369586],"iteration":155,"passed_time":1.140016799,"remaining_time":6.167783194},
{"learn":[0.4116495047],"iteration":156,"passed_time":1.147341456,"remaining_time":6.160565908},
{"learn":[0.4115040829],"iteration":157,"passed_time":1.154231111,"remaining_time":6.151029083},
{"learn":[0.4114143259],"iteration":158,"passed_time":1.16124054,"remaining_time":6.142159081},
{"learn":[0.4112839973],"iteration":159,"passed_time":1.16796248,"remaining_time":6.131803019},
{"learn":[0.411153989],"iteration":160,"passed_time":1.175998774,"remaining_time":6.128341437},
{"learn":[0.4110478525],"iteration":161,"passed_time":1.183346582,"remaining_time":6.12126195},
{"learn":[0.4109230219],"iteration":162,"passed_time":1.190452576,"remaining_time":6.112937459},
{"learn":[0.4108646629],"iteration":163,"passed_time":1.197196936,"remaining_time":6.102784379},
{"learn":[0.4107322845],"iteration":164,"passed_time":1.204276419,"remaining_time":6.094368542},
{"learn":[0.4106742158],"iteration":165,"passed_time":1.211044297,"remaining_time":6.084403275},
{"learn":[0.4105543468],"iteration":166,"passed_time":1.217744944,"remaining_time":6.074140947},
{"learn":[0.4104269168],"iteration":167,"passed_time":1.224916935,"remaining_time":6.0662553},
{"learn":[0.4102887987],"iteration":168,"passed_time":1.231730372,"remaining_time":6.056615025},
{"learn":[0.4102141164],"iteration":169,"passed_time":1.238484618,"remaining_time":6.046719015},
{"learn":[0.4101106255],"iteration":170,"passed_time":1.245851188,"remaining_time":6.039828273},
{"learn":[0.4099861102],"iteration":171,"passed_time":1.252387178,"remaining_time":6.028933627},
{"learn":[0.4098853057],"iteration":172,"passed_time":1.25960309,"remaining_time":6.021339624},
{"learn":[0.4098227804],"iteration":173,"passed_time":1.265871405,"remaining_time":6.009251612},
{"learn":[0.4097240653],"iteration":174,"passed_time":1.273003546,"remaining_time":6.001302433},
{"learn":[0.4096082384],"iteration":175,"passed_time":1.279635032,"remaining_time":5.991018559},
{"learn":[0.4094958596],"iteration":176,"passed_time":1.286678939,"remaining_time":5.982693598},
{"learn":[0.4094167529],"iteration":177,"passed_time":1.29415564,"remaining_time":5.976381661},
{"learn":[0.40932089],"iteration":178,"passed_time":1.300731442,"remaining_time":5.96592466},
{"learn":[0.4092303567],"iteration":179,"passed_time":1.307966015,"remaining_time":5.958511846},
{"learn":[0.4091355878],"iteration":180,"passed_time":1.314597187,"remaining_time":5.948370697},
{"learn":[0.4089834955],"iteration":181,"passed_time":1.322310663,"remaining_time":5.94313254},
{"learn":[0.4088649263],"iteration":182,"passed_time":1.328947519,"remaining_time":5.933060781},
{"learn":[0.4087345985],"iteration":183,"passed_time":1.336670275,"remaining_time":5.927842091},
{"learn":[0.4086334062],"iteration":184,"passed_time":1.343280621,"remaining_time":5.91769571},
{"learn":[0.4084822113],"iteration":185,"passed_time":1.349852212,"remaining_time":5.907417744},
{"learn":[0.4083493061],"iteration":186,"passed_time":1.359475277,"remaining_time":5.910445992},
{"learn":[0.4082967142],"iteration":187,"passed_time":1.367784165,"remaining_time":5.907663519},
{"learn":[0.4082269795],"iteration":188,"passed_time":1.375686329,"remaining_time":5.903077315},
{"learn":[0.4080680166],"iteration":189,"passed_time":1.384387417,"remaining_time":5.901862148},
{"learn":[0.4080090631],"iteration":190,"passed_time":1.392982916,"remaining_time":5.900121355},
{"learn":[0.4079649866],"iteration":191,"passed_time":1.401121099,"remaining_time":5.896384625},
{"learn":[0.4078927198],"iteration":192,"passed_time":1.409337289,"remaining_time":5.892928456},
{"learn":[0.4078051577],"iteration":193,"passed_time":1.41760373,"remaining_time":5.88963199},
{"learn":[0.4077337367],"iteration":194,"passed_time":1.4251588,"remaining_time":5.883347867},
{"learn":[0.4075831783],"iteration":195,"passed_time":1.43309185,"remaining_time":5.878601261},
{"learn":[0.4075172044],"iteration":196,"passed_time":1.440474545,"remaining_time":5.871578981},
{"learn":[0.4074016908],"iteration":197,"passed_time":1.447404228,"remaining_time":5.862718137},
{"learn":[0.4072951824],"iteration":198,"passed_time":1.454791235,"remaining_time":5.855717482},
{"learn":[0.407235899],"iteration":199,"passed_time":1.461352719,"remaining_time":5.845410878},
{"learn":[0.4071760497],"iteration":200,"passed_time":1.468652613,"remaining_time":5.838076805},
{"learn":[0.4070205241],"iteration":201,"passed_time":1.475464678,"remaining_time":5.828815906},
{"learn":[0.4068913259],"iteration":202,"passed_time":1.48229974,"remaining_time":5.819669421},
{"learn":[0.406834955],"iteration":203,"passed_time":1.488845917,"remaining_time":5.809418383},
{"learn":[0.4067184714],"iteration":204,"passed_time":1.496348437,"remaining_time":5.802912232},
{"learn":[0.4066246242],"iteration":205,"passed_time":1.504685409,"remaining_time":5.799612692},
{"learn":[0.4065364534],"iteration":206,"passed_time":1.511709333,"remaining_time":5.791234305},
{"learn":[0.4063581579],"iteration":207,"passed_time":1.518887649,"remaining_time":5.783456816},
{"learn":[0.4062106129],"iteration":208,"passed_time":1.52643924,"remaining_time":5.777097794},
{"learn":[0.4061520281],"iteration":209,"passed_time":1.534149437,"remaining_time":5.771324073},
{"learn":[0.4060450673],"iteration":210,"passed_time":1.542474008,"remaining_time":5.767829348},
{"learn":[0.4059527161],"iteration":211,"passed_time":1.549852693,"remaining_time":5.760773216},
{"learn":[0.4058478422],"iteration":212,"passed_time":1.556544522,"remaining_time":5.751176239},
{"learn":[0.4057757207],"iteration":213,"passed_time":1.563277433,"remaining_time":5.7417573},
{"learn":[0.4057057169],"iteration":214,"passed_time":1.570614023,"remaining_time":5.73456748},
{"learn":[0.4055781984],"iteration":215,"passed_time":1.577027365,"remaining_time":5.72402525},
{"learn":[0.4054910078],"iteration":216,"passed_time":1.58451711,"remaining_time":5.717405057},
{"learn":[0.4053971993],"iteration":217,"passed_time":1.591303802,"remaining_time":5.708254924},
{"learn":[0.4052891022],"iteration":218,"passed_time":1.598637455,"remaining_time":5.701076953},
{"learn":[0.4051702818],"iteration":219,"passed_time":1.606095647,"remaining_time":5.694339112},
{"learn":[0.4050671845],"iteration":220,"passed_time":1.612946415,"remaining_time":5.685453652},
{"learn":[0.4049646511],"iteration":221,"passed_time":1.619937103,"remaining_time":5.677076875},
{"learn":[0.404876025],"iteration":222,"passed_time":1.626392852,"remaining_time":5.666848637},
{"learn":[0.4047548997],"iteration":223,"passed_time":1.634221216,"remaining_time":5.661409213},
{"learn":[0.4046609379],"iteration":224,"passed_time":1.640852954,"remaining_time":5.651826843},
{"learn":[0.4045587716],"iteration":225,"passed_time":1.648241502,"remaining_time":5.64486249},
{"learn":[0.404473099],"iteration":226,"passed_time":1.654586389,"remaining_time":5.634340435},
{"learn":[0.4043858392],"iteration":227,"passed_time":1.661491433,"remaining_time":5.625751694},
{"learn":[0.4042531899],"iteration":228,"passed_time":1.66863036,"remaining_time":5.617965099},
{"learn":[0.4042094194],"iteration":229,"passed_time":1.674882848,"remaining_time":5.607216492},
{"learn":[0.4040550842],"iteration":230,"passed_time":1.682262128,"remaining_time":5.600257906},
{"learn":[0.4039419518],"iteration":231,"passed_time":1.688854226,"remaining_time":5.590689851},
{"learn":[0.4038847882],"iteration":232,"passed_time":1.69651293,"remaining_time":5.584658442},
{"learn":[0.4038077926],"iteration":233,"passed_time":1.704570596,"remaining_time":5.579919129},
{"learn":[0.403754884],"iteration":234,"passed_time":1.711722009,"remaining_time":5.572201434},
{"learn":[0.4036798714],"iteration":235,"passed_time":1.718227489,"remaining_time":5.562397463},
{"learn":[0.4035796637],"iteration":236,"passed_time":1.724685978,"remaining_time":5.552470046},
{"learn":[0.4034708101],"iteration":237,"passed_time":1.731935552,"remaining_time":5.545104581},
{"learn":[0.4033639611],"iteration":238,"passed_time":1.738431499,"remaining_time":5.535340462},
{"learn":[0.4032861246],"iteration":239,"passed_time":1.745979419,"remaining_time":5.528934827},
{"learn":[0.4031864704],"iteration":240,"passed_time":1.752430016,"remaining_time":5.519063827},
{"learn":[0.4031212246],"iteration":241,"passed_time":1.759112973,"remaining_time":5.5099489},
{"learn":[0.4030431796],"iteration":242,"passed_time":1.765962294,"remaining_time":5.501372249},
{"learn":[0.4029139704],"iteration":243,"passed_time":1.772597777,"remaining_time":5.492147211},
{"learn":[0.402816405],"iteration":244,"passed_time":1.779708828,"remaining_time":5.484408839},
{"learn":[0.4027483112],"iteration":245,"passed_time":1.786497379,"remaining_time":5.475687089},
{"learn":[0.4026759037],"iteration":246,"passed_time":1.793264891,"remaining_time":5.466916853},
{"learn":[0.4026036718],"iteration":247,"passed_time":1.800098939,"remaining_time":5.458364525},
{"learn":[0.4024739689],"iteration":248,"passed_time":1.806533082,"remaining_time":5.448619858},
{"learn":[0.4024056342],"iteration":249,"passed_time":1.814141475,"remaining_time":5.442424424},
{"learn":[0.402345117],"iteration":250,"passed_time":1.821106744,"remaining_time":5.434298612},
{"learn":[0.4022306442],"iteration":251,"passed_time":1.828293403,"remaining_time":5.42683915},
{"learn":[0.4020952761],"iteration":252,"passed_time":1.835037216,"remaining_time":5.418074309},
{"learn":[0.4019909007],"iteration":253,"passed_time":1.841819795,"remaining_time":5.40943924},
{"learn":[0.4018706806],"iteration":254,"passed_time":1.848699806,"remaining_time":5.401103355},
{"learn":[0.4017539652],"iteration":255,"passed_time":1.855006814,"remaining_time":5.391113554},
{"learn":[0.4015986784],"iteration":256,"passed_time":1.862052759,"remaining_time":5.383288717},
{"learn":[0.4014686346],"iteration":257,"passed_time":1.869650833,"remaining_time":5.377057823},
{"learn":[0.4013272878],"iteration":258,"passed_time":1.877117392,"remaining_time":5.370440107},
{"learn":[0.4011973676],"iteration":259,"passed_time":1.883809896,"remaining_time":5.361612782},
{"learn":[0.4010717705],"iteration":260,"passed_time":1.890405089,"remaining_time":5.352526287},
{"learn":[0.4009811666],"iteration":261,"passed_time":1.898110373,"remaining_time":5.346585708},
{"learn":[0.4008800704],"iteration":262,"passed_time":1.904527269,"remaining_time":5.337021283},
{"learn":[0.4007576257],"iteration":263,"passed_time":1.912645459,"remaining_time":5.332223705},
{"learn":[0.4007338888],"iteration":264,"passed_time":1.918666377,"remaining_time":5.321584101},
{"learn":[0.4006550796],"iteration":265,"passed_time":1.926037307,"remaining_time":5.314704448},
{"learn":[0.4005190055],"iteration":266,"passed_time":1.93249307,"remaining_time":5.305308689},
{"learn":[0.4004314547],"iteration":267,"passed_time":1.938951198,"remaining_time":5.295941331},
{"learn":[0.4002674668],"iteration":268,"passed_time":1.946196676,"remaining_time":5.288735205},
{"learn":[0.4001727022],"iteration":269,"passed_time":1.952945271,"remaining_time":5.280185363},
{"learn":[0.4000567711],"iteration":270,"passed_time":1.960502042,"remaining_time":5.273822836},
{"learn":[0.4000015851],"iteration":271,"passed_time":1.966796497,"remaining_time":5.264072977},
{"learn":[0.3999601101],"iteration":272,"passed_time":1.973823663,"remaining_time":5.256299644},
{"learn":[0.3998992034],"iteration":273,"passed_time":1.980343492,"remaining_time":5.2471875},
{"learn":[0.3997964564],"iteration":274,"passed_time":1.986748288,"remaining_time":5.23779094},
{"learn":[0.3996935913],"iteration":275,"passed_time":1.99409005,"remaining_time":5.230873899},
{"learn":[0.3995357576],"iteration":276,"passed_time":2.000837951,"remaining_time":5.22240375},
{"learn":[0.3994040972],"iteration":277,"passed_time":2.008792481,"remaining_time":5.217079753},
{"learn":[0.3993201322],"iteration":278,"passed_time":2.015427827,"remaining_time":5.208327824},
{"learn":[0.3991976303],"iteration":279,"passed_time":2.022188847,"remaining_time":5.199914179},
{"learn":[0.3990908429],"iteration":280,"passed_time":2.030317949,"remaining_time":5.195012831},
{"learn":[0.3990456978],"iteration":281,"passed_time":2.036723933,"remaining_time":5.185701362},
{"learn":[0.3989660455],"iteration":282,"passed_time":2.045022775,"remaining_time":5.181206112},
{"learn":[0.3988733892],"iteration":283,"passed_time":2.051567974,"remaining_time":5.17226292},
{"learn":[0.3987964862],"iteration":284,"passed_time":2.058753624,"remaining_time":5.164943302},
{"learn":[0.3986851291],"iteration":285,"passed_time":2.065433056,"remaining_time":5.156360845},
{"learn":[0.3985710153],"iteration":286,"passed_time":2.072646181,"remaining_time":5.149117516},
{"learn":[0.3984751867],"iteration":287,"passed_time":2.079299437,"remaining_time":5.140490275},
{"learn":[0.3983946084],"iteration":288,"passed_time":2.085724359,"remaining_time":5.131314945},
{"learn":[0.3982609305],"iteration":289,"passed_time":2.093200563,"remaining_time":5.124732412},
{"learn":[0.3981333724],"iteration":290,"passed_time":2.099520351,"remaining_time":5.115326215},
{"learn":[0.3980244253],"iteration":291,"passed_time":2.107067302,"remaining_time":5.10891661},
{"learn":[0.3979457479],"iteration":292,"passed_time":2.113641744,"remaining_time":5.100152604},
{"learn":[0.397831704],"iteration":293,"passed_time":2.120704357,"remaining_time":5.092575768},
{"learn":[0.3977552389],"iteration":294,"passed_time":2.128341537,"remaining_time":5.086375538},
{"learn":[0.3976597437],"iteration":295,"passed_time":2.134690999,"remaining_time":5.077102916},
{"learn":[0.3975646993],"iteration":296,"passed_time":2.14243312,"remaining_time":5.071146409},
{"learn":[0.3974352251],"iteration":297,"passed_time":2.148783628,"remaining_time":5.061899688},
{"learn":[0.3972942649],"iteration":298,"passed_time":2.156426826,"remaining_time":5.055703028},
{"learn":[0.3972114307],"iteration":299,"passed_time":2.162890592,"remaining_time":5.046744715},
{"learn":[0.3970879942],"iteration":300,"passed_time":2.170210196,"remaining_time":5.039790456},
{"learn":[0.3970051881],"iteration":301,"passed_time":2.176665106,"remaining_time":5.030835245},
{"learn":[0.3969473771],"iteration":302,"passed_time":2.183097325,"remaining_time":5.021844341},
{"learn":[0.3968765496],"iteration":303,"passed_time":2.190234221,"remaining_time":5.014483612},
{"learn":[0.3967640877],"iteration":304,"passed_time":2.196468198,"remaining_time":5.005066876},
{"learn":[0.3966842836],"iteration":305,"passed_time":2.205106307,"remaining_time":5.001123454},
{"learn":[0.3966069615],"iteration":306,"passed_time":2.212038166,"remaining_time":4.993297881},
{"learn":[0.3965193646],"iteration":307,"passed_time":2.219068959,"remaining_time":4.985700389},
{"learn":[0.3964084783],"iteration":308,"passed_time":2.226408925,"remaining_time":4.978797952},
{"learn":[0.39630274],"iteration":309,"passed_time":2.233011758,"remaining_time":4.970251978},
{"learn":[0.3962225088],"iteration":310,"passed_time":2.240117626,"remaining_time":4.96283294},
{"learn":[0.3961355456],"iteration":311,"passed_time":2.24649691,"remaining_time":4.953813699},
{"learn":[0.396010542],"iteration":312,"passed_time":2.253428127,"remaining_time":4.946022759},
{"learn":[0.3959138012],"iteration":313,"passed_time":2.259666198,"remaining_time":4.936722967},
{"learn":[0.395810734],"iteration":314,"passed_time":2.266082582,"remaining_time":4.927830376},
{"learn":[0.3957203257],"iteration":315,"passed_time":2.273236487,"remaining_time":4.920549865},
{"learn":[0.3956336696],"iteration":316,"passed_time":2.280588516,"remaining_time":4.913697023},
{"learn":[0.3955307075],"iteration":317,"passed_time":2.287830946,"remaining_time":4.906605991},
{"learn":[0.3954050737],"iteration":318,"passed_time":2.294346095,"remaining_time":4.897961413},
{"learn":[0.3952405642],"iteration":319,"passed_time":2.301838954,"remaining_time":4.891407777},
{"learn":[0.3951147404],"iteration":320,"passed_time":2.309024433,"remaining_time":4.8841981},
{"learn":[0.3950271325],"iteration":321,"passed_time":2.315086013,"remaining_time":4.874622101},
{"learn":[0.3949591491],"iteration":322,"passed_time":2.3221996,"remaining_time":4.867272846},
{"learn":[0.3948679702],"iteration":323,"passed_time":2.328761968,"remaining_time":4.858774971},
{"learn":[0.3947426526],"iteration":324,"passed_time":2.336169302,"remaining_time":4.852043935},
{"learn":[0.3946328928],"iteration":325,"passed_time":2.358657179,"remaining_time":4.876487542},
{"learn":[0.3945724693],"iteration":326,"passed_time":2.366462018,"remaining_time":4.870424888},
{"learn":[0.3944563287],"iteration":327,"passed_time":2.374784711,"remaining_time":4.865412579},
{"learn":[0.3943970105],"iteration":328,"passed_time":2.382841247,"remaining_time":4.859837315},
{"learn":[0.3943038591],"iteration":329,"passed_time":2.390828948,"remaining_time":4.854107259},
{"learn":[0.394242537],"iteration":330,"passed_time":2.397459715,"remaining_time":4.845620996},
{"learn":[0.3941925475],"iteration":331,"passed_time":2.404736058,"remaining_time":4.83844484},
{"learn":[0.3941023715],"iteration":332,"passed_time":2.411636433,"remaining_time":4.830515018},
{"learn":[0.3940314413],"iteration":333,"passed_time":2.419638823,"remaining_time":4.82478879},
{"learn":[0.3939423686],"iteration":334,"passed_time":2.426069248,"remaining_time":4.815928507},
{"learn":[0.3938811057],"iteration":335,"passed_time":2.433685684,"remaining_time":4.809426472},
{"learn":[0.3937882793],"iteration":336,"passed_time":2.441090076,"remaining_time":4.802500653},
{"learn":[0.3936776266],"iteration":337,"passed_time":2.448536516,"remaining_time":4.795654359},
{"learn":[0.3936370365],"iteration":338,"passed_time":2.454758731,"remaining_time":4.786417467},
{"learn":[0.3935385642],"iteration":339,"passed_time":2.461072263,"remaining_time":4.777375569},
{"learn":[0.3934066358],"iteration":340,"passed_time":2.467936572,"remaining_time":4.769414078},
{"learn":[0.3933478088],"iteration":341,"passed_time":2.474323979,"remaining_time":4.760541457},
{"learn":[0.3932446641],"iteration":342,"passed_time":2.48160788,"remaining_time":4.753400516},
{"learn":[0.3931369789],"iteration":343,"passed_time":2.487996797,"remaining_time":4.744552032},
{"learn":[0.3930459401],"iteration":344,"passed_time":2.494883543,"remaining_time":4.736662959},
{"learn":[0.3929567123],"iteration":345,"passed_time":2.501979178,"remaining_time":4.729174516},
{"learn":[0.3928743658],"iteration":346,"passed_time":2.508303118,"remaining_time":4.720236126},
{"learn":[0.3927581396],"iteration":347,"passed_time":2.515452367,"remaining_time":4.712859032},
{"learn":[0.3926370532],"iteration":348,"passed_time":2.522056315,"remaining_time":4.704466078},
{"learn":[0.3925191361],"iteration":349,"passed_time":2.528905325,"remaining_time":4.696538461},
{"learn":[0.3924106441],"iteration":350,"passed_time":2.537280435,"remaining_time":4.691438753},
{"learn":[0.3923443101],"iteration":351,"passed_time":2.544551175,"remaining_time":4.684287389},
{"learn":[0.3922722728],"iteration":352,"passed_time":2.551172518,"remaining_time":4.675945097},
{"learn":[0.3922171365],"iteration":353,"passed_time":2.557339007,"remaining_time":4.666782482},
{"learn":[0.3921170839],"iteration":354,"passed_time":2.564472626,"remaining_time":4.659393925},
{"learn":[0.3920299016],"iteration":355,"passed_time":2.571001134,"remaining_time":4.650912164},
{"learn":[0.3919174198],"iteration":356,"passed_time":2.577592716,"remaining_time":4.642554947},
{"learn":[0.3918583952],"iteration":357,"passed_time":2.584142339,"remaining_time":4.634132351},
{"learn":[0.3918016811],"iteration":358,"passed_time":2.590399115,"remaining_time":4.625197306},
{"learn":[0.3916999748],"iteration":359,"passed_time":2.597703923,"remaining_time":4.618140307},
{"learn":[0.3916143041],"iteration":360,"passed_time":2.604231199,"remaining_time":4.609705641},
{"learn":[0.3914760371],"iteration":361,"passed_time":2.611272643,"remaining_time":4.602187696},
{"learn":[0.3913204794],"iteration":362,"passed_time":2.618415,"remaining_time":4.594849463},
{"learn":[0.3912390389],"iteration":363,"passed_time":2.625458769,"remaining_time":4.587340046},
{"learn":[0.3911198669],"iteration":364,"passed_time":2.633006049,"remaining_time":4.580709154},
{"learn":[0.3910399142],"iteration":365,"passed_time":2.639300996,"remaining_time":4.571903911},
{"learn":[0.3909052918],"iteration":366,"passed_time":2.647207146,"remaining_time":4.565891345},
{"learn":[0.3908134323],"iteration":367,"passed_time":2.654337618,"remaining_time":4.558536344},
{"learn":[0.3907195023],"iteration":368,"passed_time":2.661677063,"remaining_time":4.551539911},
{"learn":[0.3906378772],"iteration":369,"passed_time":2.669716202,"remaining_time":4.545732993},
{"learn":[0.3905326962],"iteration":370,"passed_time":2.676827855,"remaining_time":4.538341565},
{"learn":[0.3903701838],"iteration":371,"passed_time":2.683820908,"remaining_time":4.530751425},
{"learn":[0.3902770455],"iteration":372,"passed_time":2.689922667,"remaining_time":4.521666252},
{"learn":[0.390184526],"iteration":373,"passed_time":2.702808054,"remaining_time":4.523951448},
{"learn":[0.3900921816],"iteration":374,"passed_time":2.70948482,"remaining_time":4.515808033},
{"learn":[0.3900178552],"iteration":375,"passed_time":2.717719344,"remaining_time":4.510257635},
{"learn":[0.3899231732],"iteration":376,"passed_time":2.724220077,"remaining_time":4.501827872},
{"learn":[0.3898380363],"iteration":377,"passed_time":2.731305669,"remaining_time":4.494370703},
{"learn":[0.389781262],"iteration":378,"passed_time":2.737554246,"remaining_time":4.485544028},
{"learn":[0.3896702353],"iteration":379,"passed_time":2.745209911,"remaining_time":4.479026697},
{"learn":[0.3895857352],"iteration":380,"passed_time":2.751977734,"remaining_time":4.471060938},
{"learn":[0.389502698],"iteration":381,"passed_time":2.758951166,"remaining_time":4.463434086},
{"learn":[0.3894166794],"iteration":382,"passed_time":2.765410809,"remaining_time":4.454982948},
{"learn":[0.3893095958],"iteration":383,"passed_time":2.771544533,"remaining_time":4.446019356},
{"learn":[0.3892074779],"iteration":384,"passed_time":2.778580776,"remaining_time":4.438512148},
{"learn":[0.3890937955],"iteration":385,"passed_time":2.785092938,"remaining_time":4.430173741},
{"learn":[0.388966779],"iteration":386,"passed_time":2.792611209,"remaining_time":4.423438427},
{"learn":[0.3888066347],"iteration":387,"passed_time":2.799266287,"remaining_time":4.415337546},
{"learn":[0.388691801],"iteration":388,"passed_time":2.805874712,"remaining_time":4.40717082},
{"learn":[0.3885422722],"iteration":389,"passed_time":2.812837941,"remaining_time":4.399567036},
{"learn":[0.3884624841],"iteration":390,"passed_time":2.819443731,"remaining_time":4.391409802},
{"learn":[0.3883776191],"iteration":391,"passed_time":2.826812825,"remaining_time":4.384444382},
{"learn":[0.3883018596],"iteration":392,"passed_time":2.83316315,"remaining_time":4.37590339},
{"learn":[0.3882209738],"iteration":393,"passed_time":2.840624753,"remaining_time":4.369082741},
{"learn":[0.3881745512],"iteration":394,"passed_time":2.848104147,"remaining_time":4.362286098},
{"learn":[0.3880361909],"iteration":395,"passed_time":2.855650168,"remaining_time":4.35558763},
{"learn":[0.3878958833],"iteration":396,"passed_time":2.863088044,"remaining_time":4.348720631},
{"learn":[0.3878146678],"iteration":397,"passed_time":2.870576929,"remaining_time":4.341927917},
{"learn":[0.3877802827],"iteration":398,"passed_time":2.878983261,"remaining_time":4.336513633},
{"learn":[0.3876942365],"iteration":399,"passed_time":2.886449083,"remaining_time":4.329673624},
{"learn":[0.3876173617],"iteration":400,"passed_time":2.893540878,"remaining_time":4.322271786},
{"learn":[0.3875937522],"iteration":401,"passed_time":2.900438345,"remaining_time":4.314582413},
{"learn":[0.3874653397],"iteration":402,"passed_time":2.908236113,"remaining_time":4.308230668},
{"learn":[0.3873405344],"iteration":403,"passed_time":2.915812999,"remaining_time":4.30154591},
{"learn":[0.3872359588],"iteration":404,"passed_time":2.923806851,"remaining_time":4.295469324},
{"learn":[0.387101484],"iteration":405,"passed_time":2.931243565,"remaining_time":4.288568171},
{"learn":[0.3869861401],"iteration":406,"passed_time":2.93930506,"remaining_time":4.282574694},
{"learn":[0.3869053996],"iteration":407,"passed_time":2.946350658,"remaining_time":4.275097034},
{"learn":[0.3867656813],"iteration":408,"passed_time":2.953279409,"remaining_time":4.267452642},
{"learn":[0.3866820752],"iteration":409,"passed_time":2.961265439,"remaining_time":4.261333193},
{"learn":[0.3866306794],"iteration":410,"passed_time":2.968286127,"remaining_time":4.253821238},
{"learn":[0.3864662158],"iteration":411,"passed_time":2.976218541,"remaining_time":4.24761287},
{"learn":[0.3863741817],"iteration":412,"passed_time":2.983213343,"remaining_time":4.240063516},
{"learn":[0.3862625218],"iteration":413,"passed_time":2.991290646,"remaining_time":4.234049079},
{"learn":[0.3861462658],"iteration":414,"passed_time":2.999138512,"remaining_time":4.227701276},
{"learn":[0.3860064672],"iteration":415,"passed_time":3.007585721,"remaining_time":4.222187647},
{"learn":[0.3859660565],"iteration":416,"passed_time":3.014630543,"remaining_time":4.214699296},
{"learn":[0.385840599],"iteration":417,"passed_time":3.021745643,"remaining_time":4.207310919},
{"learn":[0.3857259122],"iteration":418,"passed_time":3.02839603,"remaining_time":4.199279459},
{"learn":[0.3855751817],"iteration":419,"passed_time":3.037311176,"remaining_time":4.1943821},
{"learn":[0.3854734024],"iteration":420,"passed_time":3.04479996,"remaining_time":4.187503983},
{"learn":[0.3853537219],"iteration":421,"passed_time":3.052401883,"remaining_time":4.180777934},
{"learn":[0.3852910585],"iteration":422,"passed_time":3.061202039,"remaining_time":4.175682213},
{"learn":[0.3851774949],"iteration":423,"passed_time":3.06927298,"remaining_time":4.169578388},
{"learn":[0.3850656368],"iteration":424,"passed_time":3.078155058,"remaining_time":4.164562725},
{"learn":[0.3850095185],"iteration":425,"passed_time":3.086715221,"remaining_time":4.159095157},
{"learn":[0.3849052632],"iteration":426,"passed_time":3.095243401,"remaining_time":4.153570185},
{"learn":[0.3848205341],"iteration":427,"passed_time":3.103010787,"remaining_time":4.147014417},
{"learn":[0.3847391892],"iteration":428,"passed_time":3.110587196,"remaining_time":4.140198808},
{"learn":[0.3846536705],"iteration":429,"passed_time":3.118974488,"remaining_time":4.134454553},
{"learn":[0.3845381053],"iteration":430,"passed_time":3.127482182,"remaining_time":4.128856988},
{"learn":[0.3844058268],"iteration":431,"passed_time":3.137322138,"remaining_time":4.124997626},
{"learn":[0.3843158437],"iteration":432,"passed_time":3.145472298,"remaining_time":4.118897905},
{"learn":[0.3842431528],"iteration":433,"passed_time":3.153673021,"remaining_time":4.112854677},
{"learn":[0.384123808],"iteration":434,"passed_time":3.162149749,"remaining_time":4.107160019},
{"learn":[0.3840283245],"iteration":435,"passed_time":3.171207019,"remaining_time":4.102203575},
{"learn":[0.3839273491],"iteration":436,"passed_time":3.179266402,"remaining_time":4.095942756},
{"learn":[0.3838257372],"iteration":437,"passed_time":3.187378553,"remaining_time":4.089741431},
{"learn":[0.3837584041],"iteration":438,"passed_time":3.195246439,"remaining_time":4.083219253},
{"learn":[0.3836775919],"iteration":439,"passed_time":3.202989626,"remaining_time":4.076532251},
{"learn":[0.3835471476],"iteration":440,"passed_time":3.211997525,"remaining_time":4.071443574},
{"learn":[0.383472828],"iteration":441,"passed_time":3.220578557,"remaining_time":4.065798269},
{"learn":[0.3833562164],"iteration":442,"passed_time":3.229232441,"remaining_time":4.060231309},
{"learn":[0.383251369],"iteration":443,"passed_time":3.238903671,"remaining_time":4.055924416},
{"learn":[0.3831351514],"iteration":444,"passed_time":3.247196299,"remaining_time":4.049874036},
{"learn":[0.3830574539],"iteration":445,"passed_time":3.256771077,"remaining_time":4.045406226},
{"learn":[0.3830015925],"iteration":446,"passed_time":3.26351225,"remaining_time":4.037410009},
{"learn":[0.3828979926],"iteration":447,"passed_time":3.273997911,"remaining_time":4.03403314},
{"learn":[0.3828523624],"iteration":448,"passed_time":3.281404275,"remaining_time":4.026845781},
{"learn":[0.3827895173],"iteration":449,"passed_time":3.290437237,"remaining_time":4.021645512},
{"learn":[0.382687184],"iteration":450,"passed_time":3.298764359,"remaining_time":4.015569032},
{"learn":[0.3826151003],"iteration":451,"passed_time":3.307065273,"remaining_time":4.009450818},
{"learn":[0.3824994377],"iteration":452,"passed_time":3.315200463,"remaining_time":4.003122855},
{"learn":[0.382400336],"iteration":453,"passed_time":3.323574993,"remaining_time":3.997074772},
{"learn":[0.3822484523],"iteration":454,"passed_time":3.332861959,"remaining_time":3.99210938},
{"learn":[0.3821432465],"iteration":455,"passed_time":3.341624458,"remaining_time":3.986499353},
{"learn":[0.3820243975],"iteration":456,"passed_time":3.350172557,"remaining_time":3.980620785},
{"learn":[0.381899391],"iteration":457,"passed_time":3.358551595,"remaining_time":3.97453049},
{"learn":[0.3818278165],"iteration":458,"passed_time":3.367299703,"remaining_time":3.968865227},
{"learn":[0.381712987],"iteration":459,"passed_time":3.376051754,"remaining_time":3.963191189},
{"learn":[0.3816201838],"iteration":460,"passed_time":3.384578737,"remaining_time":3.957240649},
{"learn":[0.3815316797],"iteration":461,"passed_time":3.392625683,"remaining_time":3.950719951},
{"learn":[0.3814230525],"iteration":462,"passed_time":3.402587879,"remaining_time":3.94641402},
{"learn":[0.3813302258],"iteration":463,"passed_time":3.411108979,"remaining_time":3.940418993},
{"learn":[0.3812712247],"iteration":464,"passed_time":3.422150631,"remaining_time":3.937313092},
{"learn":[0.3811910437],"iteration":465,"passed_time":3.430031783,"remaining_time":3.930551442},
{"learn":[0.3810789091],"iteration":466,"passed_time":3.438418152,"remaining_time":3.924361617},
{"learn":[0.3809572921],"iteration":467,"passed_time":3.446063443,"remaining_time":3.917319982},
{"learn":[0.3808256633],"iteration":468,"passed_time":3.455075025,"remaining_time":3.911822683},
{"learn":[0.3807130319],"iteration":469,"passed_time":3.463483501,"remaining_time":3.905630331},
{"learn":[0.3806400242],"iteration":470,"passed_time":3.472238576,"remaining_time":3.899817848},
{"learn":[0.3805470438],"iteration":471,"passed_time":3.481698823,"remaining_time":3.894781734},
{"learn":[0.3804587479],"iteration":472,"passed_time":3.490226292,"remaining_time":3.888687644},
{"learn":[0.3803717248],"iteration":473,"passed_time":3.498647623,"remaining_time":3.882465505},
{"learn":[0.3803060576],"iteration":474,"passed_time":3.507010814,"remaining_time":3.876169847},
{"learn":[0.380222449],"iteration":475,"passed_time":3.517796823,"remaining_time":3.872532637},
{"learn":[0.380102192],"iteration":476,"passed_time":3.525210398,"remaining_time":3.865167795},
{"learn":[0.3800065285],"iteration":477,"passed_time":3.536052034,"remaining_time":3.861546363},
{"learn":[0.3798515807],"iteration":478,"passed_time":3.543227752,"remaining_time":3.853907429},
{"learn":[0.3797749831],"iteration":479,"passed_time":3.552521196,"remaining_time":3.848564629},
{"learn":[0.3797034097],"iteration":480,"passed_time":3.55967916,"remaining_time":3.840901214},
{"learn":[0.3796125155],"iteration":481,"passed_time":3.5696848,"remaining_time":3.836300262},
{"learn":[0.3795364332],"iteration":482,"passed_time":3.578234698,"remaining_time":3.830118714},
{"learn":[0.3794188648],"iteration":483,"passed_time":3.587692976,"remaining_time":3.824895818},
{"learn":[0.379324507],"iteration":484,"passed_time":3.596213588,"remaining_time":3.818659789},
{"learn":[0.3792077257],"iteration":485,"passed_time":3.603933454,"remaining_time":3.81156748},
{"learn":[0.3790899589],"iteration":486,"passed_time":3.612171792,"remaining_time":3.805018745},
{"learn":[0.3789891412],"iteration":487,"passed_time":3.620045626,"remaining_time":3.798080656},
{"learn":[0.3788777228],"iteration":488,"passed_time":3.627868623,"remaining_time":3.791085616},
{"learn":[0.3787800001],"iteration":489,"passed_time":3.635634251,"remaining_time":3.784027486},
{"learn":[0.3786810342],"iteration":490,"passed_time":3.642871614,"remaining_time":3.776418842},
{"learn":[0.3785482117],"iteration":491,"passed_time":3.64963686,"remaining_time":3.768324237},
{"learn":[0.3784736692],"iteration":492,"passed_time":3.655948506,"remaining_time":3.759768544},
{"learn":[0.3784207973],"iteration":493,"passed_time":3.663499255,"remaining_time":3.75249114},
{"learn":[0.3783541614],"iteration":494,"passed_time":3.670382292,"remaining_time":3.744531429},
{"learn":[0.3782784714],"iteration":495,"passed_time":3.678100553,"remaining_time":3.737424755},
{"learn":[0.3781491734],"iteration":496,"passed_time":3.685570437,"remaining_time":3.730064245},
{"learn":[0.378051025],"iteration":497,"passed_time":3.692863439,"remaining_time":3.722524993},
{"learn":[0.3779314255],"iteration":498,"passed_time":3.699955834,"remaining_time":3.714785317},
{"learn":[0.3777998227],"iteration":499,"passed_time":3.706243977,"remaining_time":3.706243977},
{"learn":[0.377732665],"iteration":500,"passed_time":3.713230241,"remaining_time":3.698406967},
{"learn":[0.3776691462],"iteration":501,"passed_time":3.719627396,"remaining_time":3.68998893},
{"learn":[0.3775447408],"iteration":502,"passed_time":3.726711529,"remaining_time":3.682257713},
{"learn":[0.3774757089],"iteration":503,"passed_time":3.733777542,"remaining_time":3.674511231},
{"learn":[0.3773812693],"iteration":504,"passed_time":3.741439645,"remaining_time":3.667351732},
{"learn":[0.3772328055],"iteration":505,"passed_time":3.748268984,"remaining_time":3.65937723},
{"learn":[0.3770721918],"iteration":506,"passed_time":3.754705993,"remaining_time":3.651025749},
{"learn":[0.3769533356],"iteration":507,"passed_time":3.761891522,"remaining_time":3.64340675},
{"learn":[0.3768197198],"iteration":508,"passed_time":3.768384166,"remaining_time":3.635121071},
{"learn":[0.3767301809],"iteration":509,"passed_time":3.775543796,"remaining_time":3.627483255},
{"learn":[0.3766606613],"iteration":510,"passed_time":3.782113611,"remaining_time":3.619282888},
{"learn":[0.3765768799],"iteration":511,"passed_time":3.788724628,"remaining_time":3.611128161},
{"learn":[0.3764670617],"iteration":512,"passed_time":3.796536935,"remaining_time":3.604119859},
{"learn":[0.3764159271],"iteration":513,"passed_time":3.80289506,"remaining_time":3.595733462},
{"learn":[0.3763035931],"iteration":514,"passed_time":3.810309133,"remaining_time":3.588349378},
{"learn":[0.3761942148],"iteration":515,"passed_time":3.816633263,"remaining_time":3.579942828},
{"learn":[0.3761189556],"iteration":516,"passed_time":3.824004732,"remaining_time":3.572522796},
{"learn":[0.3760304749],"iteration":517,"passed_time":3.83054021,"remaining_time":3.564325061},
{"learn":[0.3759326021],"iteration":518,"passed_time":3.836837049,"remaining_time":3.555912563},
{"learn":[0.3758422994],"iteration":519,"passed_time":3.854818321,"remaining_time":3.558293834},
{"learn":[0.3757757614],"iteration":520,"passed_time":3.861380423,"remaining_time":3.550098316},
{"learn":[0.3756902035],"iteration":521,"passed_time":3.867948195,"remaining_time":3.541914247},
{"learn":[0.3755761322],"iteration":522,"passed_time":3.875672941,"remaining_time":3.534791573},
{"learn":[0.3755266769],"iteration":523,"passed_time":3.882054731,"remaining_time":3.526446664},
{"learn":[0.3754326869],"iteration":524,"passed_time":3.889750771,"remaining_time":3.519298316},
{"learn":[0.3753177193],"iteration":525,"passed_time":3.897816717,"remaining_time":3.512481224},
{"learn":[0.3752629077],"iteration":526,"passed_time":3.905557499,"remaining_time":3.505367546},
{"learn":[0.3751929278],"iteration":527,"passed_time":3.912452699,"remaining_time":3.497495594},
{"learn":[0.3750945639],"iteration":528,"passed_time":3.919820686,"remaining_time":3.490048285},
{"learn":[0.3750263755],"iteration":529,"passed_time":3.926574995,"remaining_time":3.482057071},
{"learn":[0.3749458286],"iteration":530,"passed_time":3.932985817,"remaining_time":3.473767134},
{"learn":[0.3748218429],"iteration":531,"passed_time":3.940083782,"remaining_time":3.46608874},
{"learn":[0.3747334798],"iteration":532,"passed_time":3.946581111,"remaining_time":3.457886264},
{"learn":[0.3746058675],"iteration":533,"passed_time":3.954429098,"remaining_time":3.450868838},
{"learn":[0.3744611453],"iteration":534,"passed_time":3.960887865,"remaining_time":3.442640855},
{"learn":[0.3743566412],"iteration":535,"passed_time":3.967741639,"remaining_time":3.434761419},
{"learn":[0.3742169518],"iteration":536,"passed_time":3.974774171,"remaining_time":3.427039928},
{"learn":[0.3741283166],"iteration":537,"passed_time":3.981711676,"remaining_time":3.419239395},
{"learn":[0.3740435168],"iteration":538,"passed_time":3.989159496,"remaining_time":3.41187853},
{"learn":[0.373916574],"iteration":539,"passed_time":3.996174871,"remaining_time":3.404148965},
{"learn":[0.3738308801],"iteration":540,"passed_time":4.003008271,"remaining_time":3.396267646},
{"learn":[0.3737406658],"iteration":541,"passed_time":4.010422843,"remaining_time":3.388881296},
{"learn":[0.3737084028],"iteration":542,"passed_time":4.016618137,"remaining_time":3.380468671},
{"learn":[0.3736568233],"iteration":543,"passed_time":4.023852526,"remaining_time":3.372935206},
{"learn":[0.373544449],"iteration":544,"passed_time":4.035678117,"remaining_time":3.369235859},
{"learn":[0.3734497192],"iteration":545,"passed_time":4.04235848,"remaining_time":3.36122848},
{"learn":[0.3733077989],"iteration":546,"passed_time":4.049103876,"remaining_time":3.353279809},
{"learn":[0.3732505894],"iteration":547,"passed_time":4.056386871,"remaining_time":3.345778952},
{"learn":[0.3731222845],"iteration":548,"passed_time":4.064450956,"remaining_time":3.338920548},
{"learn":[0.3730016146],"iteration":549,"passed_time":4.071693286,"remaining_time":3.331385416},
{"learn":[0.3729226535],"iteration":550,"passed_time":4.078468622,"remaining_time":3.323470801},
{"learn":[0.3728590808],"iteration":551,"passed_time":4.085817685,"remaining_time":3.316025947},
{"learn":[0.3727963002],"iteration":552,"passed_time":4.092618239,"remaining_time":3.30813807},
{"learn":[0.3727465366],"iteration":553,"passed_time":4.099999263,"remaining_time":3.300721428},
{"learn":[0.3726016262],"iteration":554,"passed_time":4.107971765,"remaining_time":3.293779163},
{"learn":[0.3725179726],"iteration":555,"passed_time":4.114477764,"remaining_time":3.285662099},
{"learn":[0.3724132382],"iteration":556,"passed_time":4.123090216,"remaining_time":3.279226151},
{"learn":[0.3723163499],"iteration":557,"passed_time":4.129596759,"remaining_time":3.271114278},
{"learn":[0.3722528153],"iteration":558,"passed_time":4.138213737,"remaining_time":3.264673091},
{"learn":[0.3722026597],"iteration":559,"passed_time":4.144880846,"remaining_time":3.256692093},
{"learn":[0.3721629322],"iteration":560,"passed_time":4.152700939,"remaining_time":3.249618026},
{"learn":[0.3720772814],"iteration":561,"passed_time":4.160876491,"remaining_time":3.242818333},
{"learn":[0.3719882253],"iteration":562,"passed_time":4.169287111,"remaining_time":3.236196212},
{"learn":[0.3719182128],"iteration":563,"passed_time":4.178200605,"remaining_time":3.229956496},
{"learn":[0.3718421133],"iteration":564,"passed_time":4.186816878,"remaining_time":3.223478481},
{"learn":[0.3717854782],"iteration":565,"passed_time":4.194570557,"remaining_time":3.216331487},
{"learn":[0.3717356332],"iteration":566,"passed_time":4.202955464,"remaining_time":3.209664402},
{"learn":[0.3716826338],"iteration":567,"passed_time":4.210836416,"remaining_time":3.202607979},
{"learn":[0.3715656101],"iteration":568,"passed_time":4.22190412,"remaining_time":3.197962523},
{"learn":[0.3714713179],"iteration":569,"passed_time":4.22926814,"remaining_time":3.190500527},
{"learn":[0.3713867821],"iteration":570,"passed_time":4.239260083,"remaining_time":3.185013267},
{"learn":[0.3713358234],"iteration":571,"passed_time":4.248511398,"remaining_time":3.178956081},
{"learn":[0.3712921781],"iteration":572,"passed_time":4.25745365,"remaining_time":3.172657432},
{"learn":[0.3712297621],"iteration":573,"passed_time":4.26718268,"remaining_time":3.166933488},
{"learn":[0.3711530744],"iteration":574,"passed_time":4.276978865,"remaining_time":3.161245248},
{"learn":[0.3710843055],"iteration":575,"passed_time":4.288127797,"remaining_time":3.156538517},
{"learn":[0.3709706899],"iteration":576,"passed_time":4.297157289,"remaining_time":3.15025569},
{"learn":[0.3708581111],"iteration":577,"passed_time":4.30528095,"remaining_time":3.143302009},
{"learn":[0.3708091175],"iteration":578,"passed_time":4.313345016,"remaining_time":3.136300953},
{"learn":[0.3707252984],"iteration":579,"passed_time":4.321960248,"remaining_time":3.129695352},
{"learn":[0.3706348136],"iteration":580,"passed_time":4.330025402,"remaining_time":3.122686133},
{"learn":[0.370591212],"iteration":581,"passed_time":4.337774703,"remaining_time":3.115446437},
{"learn":[0.3705593429],"iteration":582,"passed_time":4.345757535,"remaining_time":3.108372028},
{"learn":[0.3704629789],"iteration":583,"passed_time":4.353697026,"remaining_time":3.101263635},
{"learn":[0.3704066201],"iteration":584,"passed_time":4.361485154,"remaining_time":3.094045024},
{"learn":[0.3703274512],"iteration":585,"passed_time":4.370421248,"remaining_time":3.087635489},
{"learn":[0.3702543005],"iteration":586,"passed_time":4.379282663,"remaining_time":3.081164804},
{"learn":[0.370143528],"iteration":587,"passed_time":4.387292833,"remaining_time":3.074089536},
{"learn":[0.3700901736],"iteration":588,"passed_time":4.396729418,"remaining_time":3.068006436},
{"learn":[0.3700139128],"iteration":589,"passed_time":4.404334724,"remaining_time":3.060639384},
{"learn":[0.3699832543],"iteration":590,"passed_time":4.41228921,"remaining_time":3.053513176},
{"learn":[0.3699330204],"iteration":591,"passed_time":4.419841553,"remaining_time":3.046107016},
{"learn":[0.3698690883],"iteration":592,"passed_time":4.427684433,"remaining_time":3.038899771},
{"learn":[0.3698149002],"iteration":593,"passed_time":4.434479035,"remaining_time":3.030973886},
{"learn":[0.3697208633],"iteration":594,"passed_time":4.442260685,"remaining_time":3.02372366},
{"learn":[0.3696668736],"iteration":595,"passed_time":4.4488184,"remaining_time":3.015642003},
{"learn":[0.3695875848],"iteration":596,"passed_time":4.456104639,"remaining_time":3.008057235},
{"learn":[0.3694904837],"iteration":597,"passed_time":4.463778745,"remaining_time":3.000734207},
{"learn":[0.3694360875],"iteration":598,"passed_time":4.470159314,"remaining_time":2.992544048},
{"learn":[0.3693827554],"iteration":599,"passed_time":4.477677539,"remaining_time":2.98511836},
{"learn":[0.369301658],"iteration":600,"passed_time":4.484533793,"remaining_time":2.977252884},
{"learn":[0.3692355277],"iteration":601,"passed_time":4.491833938,"remaining_time":2.969684231},
{"learn":[0.3691077792],"iteration":602,"passed_time":4.498997203,"remaining_time":2.962026351},
{"learn":[0.3690045601],"iteration":603,"passed_time":4.506253726,"remaining_time":2.954431251},
{"learn":[0.3689105542],"iteration":604,"passed_time":4.513204354,"remaining_time":2.946637554},
{"learn":[0.3688520714],"iteration":605,"passed_time":4.519605064,"remaining_time":2.938489101},
{"learn":[0.3687281721],"iteration":606,"passed_time":4.526944456,"remaining_time":2.930954154},
{"learn":[0.3686727163],"iteration":607,"passed_time":4.53350541,"remaining_time":2.922917961},
{"learn":[0.3685574526],"iteration":608,"passed_time":4.54094005,"remaining_time":2.915447553},
{"learn":[0.3684843969],"iteration":609,"passed_time":4.54736728,"remaining_time":2.907333179},
{"learn":[0.3684007358],"iteration":610,"passed_time":4.553720189,"remaining_time":2.899177011},
{"learn":[0.3682991486],"iteration":611,"passed_time":4.561350652,"remaining_time":2.891836688},
{"learn":[0.3682275824],"iteration":612,"passed_time":4.56901088,"remaining_time":2.88451421},
{"learn":[0.3681253765],"iteration":613,"passed_time":4.577021269,"remaining_time":2.877410765},
{"learn":[0.3679754005],"iteration":614,"passed_time":4.583835061,"remaining_time":2.869555282},
{"learn":[0.3679084486],"iteration":615,"passed_time":4.591225388,"remaining_time":2.862062579},
{"learn":[0.3678160655],"iteration":616,"passed_time":4.597733346,"remaining_time":2.854022482},
{"learn":[0.3677482459],"iteration":617,"passed_time":4.604437606,"remaining_time":2.846108682},
{"learn":[0.3676741797],"iteration":618,"passed_time":4.612234385,"remaining_time":2.838871245},
{"learn":[0.3675829932],"iteration":619,"passed_time":4.618532371,"remaining_time":2.830713389},
{"learn":[0.3674780385],"iteration":620,"passed_time":4.626232759,"remaining_time":2.823417417},
{"learn":[0.3674069689],"iteration":621,"passed_time":4.632501065,"remaining_time":2.815249843},
{"learn":[0.3673109053],"iteration":622,"passed_time":4.639784485,"remaining_time":2.80770265},
{"learn":[0.3672140873],"iteration":623,"passed_time":4.646150933,"remaining_time":2.799603767},
{"learn":[0.3671610494],"iteration":624,"passed_time":4.652311149,"remaining_time":2.79138669},
{"learn":[0.3671187695],"iteration":625,"passed_time":4.659018335,"remaining_time":2.783502967},
{"learn":[0.367080836],"iteration":626,"passed_time":4.665259073,"remaining_time":2.775345509},
{"learn":[0.366952747],"iteration":627,"passed_time":4.672364568,"remaining_time":2.7677064},
{"learn":[0.3668294037],"iteration":628,"passed_time":4.67894246,"remaining_time":2.759757795},
{"learn":[0.3667653104],"iteration":629,"passed_time":4.685713591,"remaining_time":2.751927029},
{"learn":[0.3666700984],"iteration":630,"passed_time":4.692940483,"remaining_time":2.744366146},
{"learn":[0.3665993801],"iteration":631,"passed_time":4.699510719,"remaining_time":2.736423963},
{"learn":[0.3664702183],"iteration":632,"passed_time":4.708718951,"remaining_time":2.730015569},
{"learn":[0.3664070728],"iteration":633,"passed_time":4.716440704,"remaining_time":2.722740217},
{"learn":[0.3663371506],"iteration":634,"passed_time":4.723623727,"remaining_time":2.715153796},
{"learn":[0.3662641623],"iteration":635,"passed_time":4.731459666,"remaining_time":2.707942324},
{"learn":[0.3661899723],"iteration":636,"passed_time":4.739355513,"remaining_time":2.700763032},
{"learn":[0.3661275816],"iteration":637,"passed_time":4.745858078,"remaining_time":2.692790947},
{"learn":[0.3660616204],"iteration":638,"passed_time":4.753235682,"remaining_time":2.685317811},
{"learn":[0.3659545119],"iteration":639,"passed_time":4.759574033,"remaining_time":2.677260393},
{"learn":[0.3658460645],"iteration":640,"passed_time":4.766132353,"remaining_time":2.669331536},
{"learn":[0.3657763369],"iteration":641,"passed_time":4.77350344,"remaining_time":2.661860174},
{"learn":[0.3656559654],"iteration":642,"passed_time":4.780439015,"remaining_time":2.654147322},
{"learn":[0.3656128885],"iteration":643,"passed_time":4.787618282,"remaining_time":2.646571597},
{"learn":[0.3654910374],"iteration":644,"passed_time":4.794181867,"remaining_time":2.638658237},
{"learn":[0.3654133612],"iteration":645,"passed_time":4.800958339,"remaining_time":2.630865715},
{"learn":[0.3653245919],"iteration":646,"passed_time":4.80797797,"remaining_time":2.623209001},
{"learn":[0.3652460356],"iteration":647,"passed_time":4.814489399,"remaining_time":2.615278192},
{"learn":[0.3651357424],"iteration":648,"passed_time":4.822510354,"remaining_time":2.608168158},
{"learn":[0.365028825],"iteration":649,"passed_time":4.829289945,"remaining_time":2.600386893},
{"learn":[0.3649245336],"iteration":650,"passed_time":4.83726733,"remaining_time":2.593250842},
{"learn":[0.3648931967],"iteration":651,"passed_time":4.844538923,"remaining_time":2.585735499},
{"learn":[0.3648231205],"iteration":652,"passed_time":4.852542324,"remaining_time":2.57860978},
{"learn":[0.3647312802],"iteration":653,"passed_time":4.859391446,"remaining_time":2.570870704},
{"learn":[0.3646861632],"iteration":654,"passed_time":4.866311474,"remaining_time":2.563171692},
{"learn":[0.3645973629],"iteration":655,"passed_time":4.87345046,"remaining_time":2.555589875},
{"learn":[0.3644957113],"iteration":656,"passed_time":4.879832761,"remaining_time":2.547614364},
{"learn":[0.3644355892],"iteration":657,"passed_time":4.887109926,"remaining_time":2.540108807},
{"learn":[0.3643640023],"iteration":658,"passed_time":4.893377116,"remaining_time":2.53208133},
{"learn":[0.364301877],"iteration":659,"passed_time":4.900499337,"remaining_time":2.524499658},
{"learn":[0.3642138369],"iteration":660,"passed_time":4.908272474,"remaining_time":2.517253205},
{"learn":[0.364156851],"iteration":661,"passed_time":4.915702391,"remaining_time":2.509829922},
{"learn":[0.3640566118],"iteration":662,"passed_time":4.923325695,"remaining_time":2.502504916},
{"learn":[0.3639857333],"iteration":663,"passed_time":4.929760426,"remaining_time":2.494577565},
{"learn":[0.3639259447],"iteration":664,"passed_time":4.937431191,"remaining_time":2.487277367},
{"learn":[0.3638665145],"iteration":665,"passed_time":4.943795297,"remaining_time":2.479320765},
{"learn":[0.3637842992],"iteration":666,"passed_time":4.951203317,"remaining_time":2.471890112},
{"learn":[0.3637272347],"iteration":667,"passed_time":4.957966463,"remaining_time":2.464139021},
{"learn":[0.363601136],"iteration":668,"passed_time":4.966163816,"remaining_time":2.457100483},
{"learn":[0.3635543396],"iteration":669,"passed_time":4.972737818,"remaining_time":2.449258925},
{"learn":[0.36344981],"iteration":670,"passed_time":4.979268291,"remaining_time":2.441399803},
{"learn":[0.3633950157],"iteration":671,"passed_time":4.986268737,"remaining_time":2.433774026},
{"learn":[0.3632895976],"iteration":672,"passed_time":4.992730552,"remaining_time":2.425888396},
{"learn":[0.3631768712],"iteration":673,"passed_time":5.001295536,"remaining_time":2.41902425},
{"learn":[0.3631113543],"iteration":674,"passed_time":5.007633477,"remaining_time":2.411082785},
{"learn":[0.3630252711],"iteration":675,"passed_time":5.015567188,"remaining_time":2.403910901},
{"learn":[0.3629468345],"iteration":676,"passed_time":5.022794686,"remaining_time":2.396399828},
{"learn":[0.362904884],"iteration":677,"passed_time":5.029442862,"remaining_time":2.388614457},
{"learn":[0.3628083429],"iteration":678,"passed_time":5.036080956,"remaining_time":2.380827668},
{"learn":[0.3627510857],"iteration":679,"passed_time":5.042334991,"remaining_time":2.372863525},
{"learn":[0.3626658133],"iteration":680,"passed_time":5.049341115,"remaining_time":2.365256704},
{"learn":[0.3625302328],"iteration":681,"passed_time":5.055775814,"remaining_time":2.357385204},
{"learn":[0.3623754166],"iteration":682,"passed_time":5.063084309,"remaining_time":2.349923464},
{"learn":[0.3623112305],"iteration":683,"passed_time":5.069598861,"remaining_time":2.34209538},
{"learn":[0.3621922306],"iteration":684,"passed_time":5.076438221,"remaining_time":2.334420496},
{"learn":[0.3621001769],"iteration":685,"passed_time":5.084713109,"remaining_time":2.327405126},
{"learn":[0.3620137481],"iteration":686,"passed_time":5.092754194,"remaining_time":2.320279567},
{"learn":[0.3619013156],"iteration":687,"passed_time":5.100082123,"remaining_time":2.31282794},
{"learn":[0.3617954478],"iteration":688,"passed_time":5.107169398,"remaining_time":2.305268045},
{"learn":[0.3617305723],"iteration":689,"passed_time":5.114181915,"remaining_time":2.297675933},
{"learn":[0.3616682654],"iteration":690,"passed_time":5.120629149,"remaining_time":2.289832716},
{"learn":[0.3615689789],"iteration":691,"passed_time":5.127498471,"remaining_time":2.2821814},
{"learn":[0.3614664646],"iteration":692,"passed_time":5.135284615,"remaining_time":2.274938495},
{"learn":[0.3613479638],"iteration":693,"passed_time":5.141894208,"remaining_time":2.267175256},
{"learn":[0.36123951],"iteration":694,"passed_time":5.149310427,"remaining_time":2.259769324},
{"learn":[0.3611507386],"iteration":695,"passed_time":5.155985821,"remaining_time":2.252039784},
{"learn":[0.3610555527],"iteration":696,"passed_time":5.162893688,"remaining_time":2.244414329},
{"learn":[0.3610094568],"iteration":697,"passed_time":5.169321196,"remaining_time":2.236583096},
{"learn":[0.3609099395],"iteration":698,"passed_time":5.176156643,"remaining_time":2.228931544},
{"learn":[0.3608669502],"iteration":699,"passed_time":5.183010718,"remaining_time":2.221290308},
{"learn":[0.3607662422],"iteration":700,"passed_time":5.189642472,"remaining_time":2.213556489},
{"learn":[0.3606784692],"iteration":701,"passed_time":5.197326741,"remaining_time":2.206272605},
{"learn":[0.3605646159],"iteration":702,"passed_time":5.204051811,"remaining_time":2.198582344},
{"learn":[0.3604855735],"iteration":703,"passed_time":5.21165072,"remaining_time":2.191262235},
{"learn":[0.3604062166],"iteration":704,"passed_time":5.218250834,"remaining_time":2.183523399},
{"learn":[0.3603109143],"iteration":705,"passed_time":5.224392778,"remaining_time":2.175596993},
{"learn":[0.360214293],"iteration":706,"passed_time":5.233193738,"remaining_time":2.168777603},
{"learn":[0.3601205139],"iteration":707,"passed_time":5.239624005,"remaining_time":2.160974872},
{"learn":[0.3600395186],"iteration":708,"passed_time":5.247903333,"remaining_time":2.153934936},
{"learn":[0.3599812844],"iteration":709,"passed_time":5.25435705,"remaining_time":2.146145837},
{"learn":[0.3598587707],"iteration":710,"passed_time":5.261897965,"remaining_time":2.138802408},
{"learn":[0.3597862176],"iteration":711,"passed_time":5.268625451,"remaining_time":2.131129396},
{"learn":[0.3597206031],"iteration":712,"passed_time":5.275952395,"remaining_time":2.123700333},
{"learn":[0.3596897401],"iteration":713,"passed_time":5.282208548,"remaining_time":2.11584264},
{"learn":[0.3596438027],"iteration":714,"passed_time":5.288575565,"remaining_time":2.108033617},
{"learn":[0.359600861],"iteration":715,"passed_time":5.295785991,"remaining_time":2.100563159},
{"learn":[0.3595106624],"iteration":716,"passed_time":5.302153496,"remaining_time":2.092760724},
{"learn":[0.3594435185],"iteration":717,"passed_time":5.309604351,"remaining_time":2.085387781},
{"learn":[0.3593530974],"iteration":718,"passed_time":5.316763498,"remaining_time":2.077900616},
{"learn":[0.3592943963],"iteration":719,"passed_time":5.32382294,"remaining_time":2.070375588},
{"learn":[0.359233446],"iteration":720,"passed_time":5.331450187,"remaining_time":2.06307157},
{"learn":[0.35913662],"iteration":721,"passed_time":5.339222754,"remaining_time":2.055822612},
{"learn":[0.3590633929],"iteration":722,"passed_time":5.346450197,"remaining_time":2.048363354},
{"learn":[0.3590106232],"iteration":723,"passed_time":5.353139294,"remaining_time":2.04069951},
{"learn":[0.3589128872],"iteration":724,"passed_time":5.361041495,"remaining_time":2.033498498},
{"learn":[0.358811573],"iteration":725,"passed_time":5.368727363,"remaining_time":2.026213908},
{"learn":[0.3587045514],"iteration":726,"passed_time":5.376459881,"remaining_time":2.018945732},
{"learn":[0.3586323703],"iteration":727,"passed_time":5.383511202,"remaining_time":2.011421768},
{"learn":[0.3585219888],"iteration":728,"passed_time":5.391434177,"remaining_time":2.00422313},
{"learn":[0.3584297088],"iteration":729,"passed_time":5.398816849,"remaining_time":1.99682267},
{"learn":[0.3583574955],"iteration":730,"passed_time":5.406301017,"remaining_time":1.989459608},
{"learn":[0.3582663951],"iteration":731,"passed_time":5.413863867,"remaining_time":1.982125022},
{"learn":[0.3581470788],"iteration":732,"passed_time":5.420579303,"remaining_time":1.974481138},
{"learn":[0.3580893244],"iteration":733,"passed_time":5.427733318,"remaining_time":1.966998723},
{"learn":[0.3580296298],"iteration":734,"passed_time":5.435616063,"remaining_time":1.959779941},
{"learn":[0.3579740717],"iteration":735,"passed_time":5.443782819,"remaining_time":1.952661229},
{"learn":[0.3579394816],"iteration":736,"passed_time":5.451084916,"remaining_time":1.945231117},
{"learn":[0.3578304999],"iteration":737,"passed_time":5.459121586,"remaining_time":1.938062135},
{"learn":[0.3577464351],"iteration":738,"passed_time":5.466314803,"remaining_time":1.930592914},
{"learn":[0.3576681157],"iteration":739,"passed_time":5.474055033,"remaining_time":1.923316633},
{"learn":[0.3576033453],"iteration":740,"passed_time":5.483488714,"remaining_time":1.916631008},
{"learn":[0.3574905832],"iteration":741,"passed_time":5.491863496,"remaining_time":1.909569787},
{"learn":[0.3574136446],"iteration":742,"passed_time":5.498667334,"remaining_time":1.901961648},
{"learn":[0.3573147266],"iteration":743,"passed_time":5.507505652,"remaining_time":1.895055708},
{"learn":[0.357246694],"iteration":744,"passed_time":5.514285112,"remaining_time":1.887439871},
{"learn":[0.3572151128],"iteration":745,"passed_time":5.52239526,"remaining_time":1.880279351},
{"learn":[0.3571098142],"iteration":746,"passed_time":5.530250732,"remaining_time":1.873030034},
{"learn":[0.3570595032],"iteration":747,"passed_time":5.53880748,"remaining_time":1.866015354},
{"learn":[0.3570173692],"iteration":748,"passed_time":5.546208314,"remaining_time":1.858609195},
{"learn":[0.3569924829],"iteration":749,"passed_time":5.554967477,"remaining_time":1.851655826},
{"learn":[0.3568732949],"iteration":750,"passed_time":5.563149825,"remaining_time":1.8445064},
{"learn":[0.3567888969],"iteration":751,"passed_time":5.571756518,"remaining_time":1.837494171},
{"learn":[0.3567170627],"iteration":752,"passed_time":5.590614292,"remaining_time":1.833840279},
{"learn":[0.3566952837],"iteration":753,"passed_time":5.598125769,"remaining_time":1.826444216},
{"learn":[0.3565829313],"iteration":754,"passed_time":5.607036401,"remaining_time":1.819501879},
{"learn":[0.3565003462],"iteration":755,"passed_time":5.615086254,"remaining_time":1.812276516},
{"learn":[0.3564330106],"iteration":756,"passed_time":5.62401913,"remaining_time":1.805332429},
{"learn":[0.3563993956],"iteration":757,"passed_time":5.631285252,"remaining_time":1.797850964},
{"learn":[0.3563388348],"iteration":758,"passed_time":5.639299162,"remaining_time":1.790607507},
{"learn":[0.3562463601],"iteration":759,"passed_time":5.647137849,"remaining_time":1.783306689},
{"learn":[0.3561703993],"iteration":760,"passed_time":5.655846063,"remaining_time":1.776277542},
{"learn":[0.3560952675],"iteration":761,"passed_time":5.664015231,"remaining_time":1.769075623},
{"learn":[0.3559868985],"iteration":762,"passed_time":5.672406562,"remaining_time":1.761940177},
{"learn":[0.355895255],"iteration":763,"passed_time":5.679962654,"remaining_time":1.754543438},
{"learn":[0.355854654],"iteration":764,"passed_time":5.688173686,"remaining_time":1.747347472},
{"learn":[0.3557706728],"iteration":765,"passed_time":5.69594266,"remaining_time":1.740013815},
{"learn":[0.3556798663],"iteration":766,"passed_time":5.704276737,"remaining_time":1.732850691},
{"learn":[0.3556209963],"iteration":767,"passed_time":5.712197265,"remaining_time":1.72555959},
{"learn":[0.3555092582],"iteration":768,"passed_time":5.721006077,"remaining_time":1.718533685},
{"learn":[0.3554432223],"iteration":769,"passed_time":5.728579967,"remaining_time":1.711134276},
{"learn":[0.3554256154],"iteration":770,"passed_time":5.736677372,"remaining_time":1.703889907},
{"learn":[0.3553583481],"iteration":771,"passed_time":5.745516088,"remaining_time":1.696862264},
{"learn":[0.3552898887],"iteration":772,"passed_time":5.753339986,"remaining_time":1.689531923},
{"learn":[0.3552201499],"iteration":773,"passed_time":5.76100514,"remaining_time":1.682153956},
{"learn":[0.3551112436],"iteration":774,"passed_time":5.769740158,"remaining_time":1.675085852},
{"learn":[0.3550550587],"iteration":775,"passed_time":5.777932513,"remaining_time":1.667856808},
{"learn":[0.3550116101],"iteration":776,"passed_time":5.786736777,"remaining_time":1.660800903},
{"learn":[0.3549077269],"iteration":777,"passed_time":5.794454385,"remaining_time":1.653430429},
{"learn":[0.3548370266],"iteration":778,"passed_time":5.807053914,"remaining_time":1.64744405},
{"learn":[0.3547576567],"iteration":779,"passed_time":5.814449738,"remaining_time":1.639973003},
{"learn":[0.35464864],"iteration":780,"passed_time":5.823333936,"remaining_time":1.632919503},
{"learn":[0.3545557011],"iteration":781,"passed_time":5.831901659,"remaining_time":1.625773097},
{"learn":[0.3544668055],"iteration":782,"passed_time":5.840838495,"remaining_time":1.618725356},
{"learn":[0.3544034615],"iteration":783,"passed_time":5.850204994,"remaining_time":1.611791172},
{"learn":[0.3543367449],"iteration":784,"passed_time":5.858461184,"remaining_time":1.604546694},
{"learn":[0.3542285627],"iteration":785,"passed_time":5.867649339,"remaining_time":1.597553382},
{"learn":[0.3541514312],"iteration":786,"passed_time":5.875470503,"remaining_time":1.59018452},
{"learn":[0.354040091],"iteration":787,"passed_time":5.88487128,"remaining_time":1.583239482},
{"learn":[0.3540252386],"iteration":788,"passed_time":5.891507109,"remaining_time":1.575548796},
{"learn":[0.3539733378],"iteration":789,"passed_time":5.899954953,"remaining_time":1.568342456},
{"learn":[0.3538606022],"iteration":790,"passed_time":5.908299542,"remaining_time":1.561105694},
{"learn":[0.3537988072],"iteration":791,"passed_time":5.917596496,"remaining_time":1.554116252},
{"learn":[0.3537254394],"iteration":792,"passed_time":5.925824975,"remaining_time":1.546842081},
{"learn":[0.3536248786],"iteration":793,"passed_time":5.933862776,"remaining_time":1.539516035},
{"learn":[0.3535063023],"iteration":794,"passed_time":5.941873498,"remaining_time":1.532181217},
{"learn":[0.3534469921],"iteration":795,"passed_time":5.950818789,"remaining_time":1.525084212},
{"learn":[0.3534048276],"iteration":796,"passed_time":5.958459645,"remaining_time":1.517650324},
{"learn":[0.3533139656],"iteration":797,"passed_time":5.966843609,"remaining_time":1.510404021},
{"learn":[0.3532053892],"iteration":798,"passed_time":5.974640528,"remaining_time":1.503007192},
{"learn":[0.3531239181],"iteration":799,"passed_time":5.982598442,"remaining_time":1.495649611},
{"learn":[0.3530287098],"iteration":800,"passed_time":5.989933572,"remaining_time":1.488135806},
{"learn":[0.3529493202],"iteration":801,"passed_time":5.998710508,"remaining_time":1.480978405},
{"learn":[0.3528783597],"iteration":802,"passed_time":6.00690137,"remaining_time":1.473673188},
{"learn":[0.3528474135],"iteration":803,"passed_time":6.015021777,"remaining_time":1.466348592},
{"learn":[0.3527736386],"iteration":804,"passed_time":6.022158066,"remaining_time":1.458783631},
{"learn":[0.3527217043],"iteration":805,"passed_time":6.031366436,"remaining_time":1.451718472},
{"learn":[0.3526390702],"iteration":806,"passed_time":6.03986016,"remaining_time":1.444477089},
{"learn":[0.3525284165],"iteration":807,"passed_time":6.048637055,"remaining_time":1.437299894},
{"learn":[0.3524625667],"iteration":808,"passed_time":6.055767414,"remaining_time":1.429730008},
{"learn":[0.3523685309],"iteration":809,"passed_time":6.064019349,"remaining_time":1.422424292},
{"learn":[0.3522800278],"iteration":810,"passed_time":6.072231158,"remaining_time":1.415106891},
{"learn":[0.3522104835],"iteration":811,"passed_time":6.080477117,"remaining_time":1.407795195},
{"learn":[0.3521418307],"iteration":812,"passed_time":6.088624787,"remaining_time":1.400458592},
{"learn":[0.3520706975],"iteration":813,"passed_time":6.09755156,"remaining_time":1.393298022},
{"learn":[0.3519372602],"iteration":814,"passed_time":6.105940732,"remaining_time":1.386011086},
{"learn":[0.3518221242],"iteration":815,"passed_time":6.114429731,"remaining_time":1.378743959},
{"learn":[0.3517637267],"iteration":816,"passed_time":6.121147202,"remaining_time":1.371077036},
{"learn":[0.3516585041],"iteration":817,"passed_time":6.130370845,"remaining_time":1.363970041},
{"learn":[0.351619793],"iteration":818,"passed_time":6.137448007,"remaining_time":1.356383503},
{"learn":[0.3515756943],"iteration":819,"passed_time":6.145339731,"remaining_time":1.348977014},
{"learn":[0.3514913719],"iteration":820,"passed_time":6.152700205,"remaining_time":1.341453516},
{"learn":[0.3513976333],"iteration":821,"passed_time":6.160467623,"remaining_time":1.334018536},
{"learn":[0.3513105381],"iteration":822,"passed_time":6.167993107,"remaining_time":1.326530717},
{"learn":[0.3511945528],"iteration":823,"passed_time":6.175191777,"remaining_time":1.318973001},
{"learn":[0.3511149468],"iteration":824,"passed_time":6.182302611,"remaining_time":1.311397524},
{"learn":[0.3510100799],"iteration":825,"passed_time":6.189552949,"remaining_time":1.303852558},
{"learn":[0.350898304],"iteration":826,"passed_time":6.197029999,"remaining_time":1.296355731},
{"learn":[0.350803683],"iteration":827,"passed_time":6.203974119,"remaining_time":1.288748247},
{"learn":[0.3507598634],"iteration":828,"passed_time":6.211621489,"remaining_time":1.281287424},
{"learn":[0.3507275631],"iteration":829,"passed_time":6.218670406,"remaining_time":1.273703577},
{"learn":[0.3506435402],"iteration":830,"passed_time":6.226701368,"remaining_time":1.266320735},
{"learn":[0.3505487312],"iteration":831,"passed_time":6.233987067,"remaining_time":1.25878585},
{"learn":[0.3504937529],"iteration":832,"passed_time":6.241859757,"remaining_time":1.251369243},
{"learn":[0.3504289971],"iteration":833,"passed_time":6.250626193,"remaining_time":1.244129434},
{"learn":[0.3503814465],"iteration":834,"passed_time":6.259068292,"remaining_time":1.236821878},
{"learn":[0.3502825511],"iteration":835,"passed_time":6.267325224,"remaining_time":1.229475283},
{"learn":[0.3502053523],"iteration":836,"passed_time":6.275067308,"remaining_time":1.22202625},
{"learn":[0.3501259413],"iteration":837,"passed_time":6.283492244,"remaining_time":1.214708525},
{"learn":[0.3500810315],"iteration":838,"passed_time":6.29059959,"remaining_time":1.207135321},
{"learn":[0.3500130297],"iteration":839,"passed_time":6.298351924,"remaining_time":1.199686081},
{"learn":[0.3499090157],"iteration":840,"passed_time":6.305169247,"remaining_time":1.192059346},
{"learn":[0.3498136821],"iteration":841,"passed_time":6.31334382,"remaining_time":1.18468922},
{"learn":[0.3496942829],"iteration":842,"passed_time":6.320754057,"remaining_time":1.177174836},
{"learn":[0.349599028],"iteration":843,"passed_time":6.32837934,"remaining_time":1.169700447},
{"learn":[0.3495374754],"iteration":844,"passed_time":6.334967056,"remaining_time":1.162035377},
{"learn":[0.3494344747],"iteration":845,"passed_time":6.343820716,"remaining_time":1.154785331},
{"learn":[0.3493626115],"iteration":846,"passed_time":6.35121133,"remaining_time":1.147267218},
{"learn":[0.3492762317],"iteration":847,"passed_time":6.359469629,"remaining_time":1.139904934},
{"learn":[0.3491326997],"iteration":848,"passed_time":6.366470354,"remaining_time":1.132316871},
{"learn":[0.3490474204],"iteration":849,"passed_time":6.37399702,"remaining_time":1.124823004},
{"learn":[0.3489845614],"iteration":850,"passed_time":6.380964392,"remaining_time":1.117231133},
{"learn":[0.3488826387],"iteration":851,"passed_time":6.388363774,"remaining_time":1.109715773},
{"learn":[0.3488276809],"iteration":852,"passed_time":6.395377559,"remaining_time":1.102134233},
{"learn":[0.3487170463],"iteration":853,"passed_time":6.402704763,"remaining_time":1.094607606},
{"learn":[0.3486244071],"iteration":854,"passed_time":6.410475724,"remaining_time":1.087156702},
{"learn":[0.3485268192],"iteration":855,"passed_time":6.419557952,"remaining_time":1.079925637},
{"learn":[0.3484415065],"iteration":856,"passed_time":6.428642799,"remaining_time":1.072690689},
{"learn":[0.3483270655],"iteration":857,"passed_time":6.436391587,"remaining_time":1.065230309},
{"learn":[0.348286817],"iteration":858,"passed_time":6.445027238,"remaining_time":1.057914832},
{"learn":[0.3482532109],"iteration":859,"passed_time":6.451550302,"remaining_time":1.050252375},
{"learn":[0.3482217131],"iteration":860,"passed_time":6.460298231,"remaining_time":1.042951747},
{"learn":[0.3481044003],"iteration":861,"passed_time":6.46787691,"remaining_time":1.035460573},
{"learn":[0.3480686962],"iteration":862,"passed_time":6.476202898,"remaining_time":1.02808783},
{"learn":[0.3480473591],"iteration":863,"passed_time":6.48347122,"remaining_time":1.020546396},
{"learn":[0.3480016657],"iteration":864,"passed_time":6.492890915,"remaining_time":1.013341357},
{"learn":[0.3479000025],"iteration":865,"passed_time":6.501008281,"remaining_time":1.005929688},
{"learn":[0.347833966],"iteration":866,"passed_time":6.50947246,"remaining_time":0.998569593},
{"learn":[0.347761168],"iteration":867,"passed_time":6.516477882,"remaining_time":0.9909851157},
{"learn":[0.3476937973],"iteration":868,"passed_time":6.524990717,"remaining_time":0.9836292105},
{"learn":[0.3476032568],"iteration":869,"passed_time":6.532184793,"remaining_time":0.9760735897},
{"learn":[0.3474973801],"iteration":870,"passed_time":6.541618665,"remaining_time":0.9688505256},
{"learn":[0.347425684],"iteration":871,"passed_time":6.549607076,"remaining_time":0.961410213},
{"learn":[0.3473313782],"iteration":872,"passed_time":6.558842604,"remaining_time":0.9541500695},
{"learn":[0.3472696408],"iteration":873,"passed_time":6.56664914,"remaining_time":0.9466793955},
{"learn":[0.3472202515],"iteration":874,"passed_time":6.57453968,"remaining_time":0.9392199542},
{"learn":[0.347159378],"iteration":875,"passed_time":6.582169885,"remaining_time":0.9317226778},
{"learn":[0.3471051188],"iteration":876,"passed_time":6.591401633,"remaining_time":0.924449716},
{"learn":[0.3470532867],"iteration":877,"passed_time":6.59862215,"remaining_time":0.9168928272},
{"learn":[0.3469377424],"iteration":878,"passed_time":6.608289185,"remaining_time":0.9096734828},
{"learn":[0.3468750237],"iteration":879,"passed_time":6.616248917,"remaining_time":0.9022157614},
{"learn":[0.3467698566],"iteration":880,"passed_time":6.624784181,"remaining_time":0.8948346397},
{"learn":[0.3467233442],"iteration":881,"passed_time":6.632668955,"remaining_time":0.8873638738},
{"learn":[0.346662919],"iteration":882,"passed_time":6.640837621,"remaining_time":0.8799297867},
{"learn":[0.3465697006],"iteration":883,"passed_time":6.649316119,"remaining_time":0.8725346944},
{"learn":[0.3465241183],"iteration":884,"passed_time":6.657464131,"remaining_time":0.8650942091},
{"learn":[0.3464745573],"iteration":885,"passed_time":6.664772035,"remaining_time":0.8575440316},
{"learn":[0.3464275283],"iteration":886,"passed_time":6.673824542,"remaining_time":0.8502166553},
{"learn":[0.3463467028],"iteration":887,"passed_time":6.681594876,"remaining_time":0.8427236781},
{"learn":[0.3462531926],"iteration":888,"passed_time":6.690491713,"remaining_time":0.8353707314},
{"learn":[0.3461809849],"iteration":889,"passed_time":6.697855253,"remaining_time":0.8278248066},
{"learn":[0.3461186924],"iteration":890,"passed_time":6.708883869,"remaining_time":0.8207276562},
{"learn":[0.346056333],"iteration":891,"passed_time":6.717123029,"remaining_time":0.8132839542},
{"learn":[0.3459339035],"iteration":892,"passed_time":6.724540698,"remaining_time":0.8057400389},
{"learn":[0.3458756137],"iteration":893,"passed_time":6.731278764,"remaining_time":0.7981158266},
{"learn":[0.3458309186],"iteration":894,"passed_time":6.739057905,"remaining_time":0.7906157319},
{"learn":[0.3457015998],"iteration":895,"passed_time":6.745955153,"remaining_time":0.7830126517},
{"learn":[0.3456479333],"iteration":896,"passed_time":6.75582588,"remaining_time":0.7757525815},
{"learn":[0.3455393948],"iteration":897,"passed_time":6.763436533,"remaining_time":0.7682299848},
{"learn":[0.3454729414],"iteration":898,"passed_time":6.770993361,"remaining_time":0.7607011451},
{"learn":[0.3454091265],"iteration":899,"passed_time":6.77815657,"remaining_time":0.7531285078},
{"learn":[0.3453463028],"iteration":900,"passed_time":6.786809166,"remaining_time":0.74572043},
{"learn":[0.3452721843],"iteration":901,"passed_time":6.793599687,"remaining_time":0.738107283},
{"learn":[0.3452496311],"iteration":902,"passed_time":6.801146833,"remaining_time":0.7305772346},
{"learn":[0.3451630166],"iteration":903,"passed_time":6.808430008,"remaining_time":0.7230191159},
{"learn":[0.3450906429],"iteration":904,"passed_time":6.81612506,"remaining_time":0.7155048406},
{"learn":[0.3450071303],"iteration":905,"passed_time":6.82347847,"remaining_time":0.7079547198},
{"learn":[0.3449621968],"iteration":906,"passed_time":6.830369705,"remaining_time":0.7003576434},
{"learn":[0.3449003961],"iteration":907,"passed_time":6.837327308,"remaining_time":0.6927688462},
{"learn":[0.3448654323],"iteration":908,"passed_time":6.84407623,"remaining_time":0.6851605467},
{"learn":[0.3447893849],"iteration":909,"passed_time":6.852266638,"remaining_time":0.6776967005},
{"learn":[0.3446954069],"iteration":910,"passed_time":6.859304925,"remaining_time":0.6701187029},
{"learn":[0.3446638058],"iteration":911,"passed_time":6.866088416,"remaining_time":0.6625173033},
{"learn":[0.3445660369],"iteration":912,"passed_time":6.87333117,"remaining_time":0.6549614587},
{"learn":[0.3445421008],"iteration":913,"passed_time":6.880458551,"remaining_time":0.6473954436},
{"learn":[0.3445271151],"iteration":914,"passed_time":6.887238957,"remaining_time":0.6397981545},
{"learn":[0.3444570926],"iteration":915,"passed_time":6.894406176,"remaining_time":0.632238121},
{"learn":[0.34440108],"iteration":916,"passed_time":6.903062477,"remaining_time":0.6248137247},
{"learn":[0.3443050931],"iteration":917,"passed_time":6.910310669,"remaining_time":0.6172608658},
{"learn":[0.3442445094],"iteration":918,"passed_time":6.917792485,"remaining_time":0.6097292615},
{"learn":[0.3442112478],"iteration":919,"passed_time":6.925186532,"remaining_time":0.6021901332},
{"learn":[0.3441527227],"iteration":920,"passed_time":6.932917395,"remaining_time":0.5946802108},
{"learn":[0.3440380252],"iteration":921,"passed_time":6.941853845,"remaining_time":0.5872718003},
{"learn":[0.3439812768],"iteration":922,"passed_time":6.950644391,"remaining_time":0.579847907},
{"learn":[0.3439134039],"iteration":923,"passed_time":6.95791436,"remaining_time":0.5722959863},
{"learn":[0.3438643991],"iteration":924,"passed_time":6.966187974,"remaining_time":0.564826052},
{"learn":[0.3437898336],"iteration":925,"passed_time":6.973882122,"remaining_time":0.5573080746},
{"learn":[0.3437224341],"iteration":926,"passed_time":6.980930004,"remaining_time":0.5497388245},
{"learn":[0.3437047912],"iteration":927,"passed_time":6.987250729,"remaining_time":0.5421142807},
{"learn":[0.3436358965],"iteration":928,"passed_time":6.994381163,"remaining_time":0.5345544269},
{"learn":[0.3435628661],"iteration":929,"passed_time":7.000941562,"remaining_time":0.5269525907},
{"learn":[0.3434772651],"iteration":930,"passed_time":7.008247628,"remaining_time":0.519408256},
{"learn":[0.3434044127],"iteration":931,"passed_time":7.014689225,"remaining_time":0.5118013598},
{"learn":[0.3433732759],"iteration":932,"passed_time":7.02147131,"remaining_time":0.5042214124},
{"learn":[0.3433377531],"iteration":933,"passed_time":7.028045934,"remaining_time":0.4966285135},
{"learn":[0.3432241863],"iteration":934,"passed_time":7.034793994,"remaining_time":0.4890498498},
{"learn":[0.3431502861],"iteration":935,"passed_time":7.04213516,"remaining_time":0.4815135152},
{"learn":[0.3431108821],"iteration":936,"passed_time":7.048244492,"remaining_time":0.4738947737},
{"learn":[0.343046124],"iteration":937,"passed_time":7.0557768,"remaining_time":0.4663733066},
{"learn":[0.3429490934],"iteration":938,"passed_time":7.063925759,"remaining_time":0.4588918757},
{"learn":[0.3429021318],"iteration":939,"passed_time":7.071964285,"remaining_time":0.4514019756},
{"learn":[0.3428019989],"iteration":940,"passed_time":7.078941658,"remaining_time":0.443844376},
{"learn":[0.3427277296],"iteration":941,"passed_time":7.086022616,"remaining_time":0.4362943861},
{"learn":[0.3426484918],"iteration":942,"passed_time":7.093563253,"remaining_time":0.4287731765},
{"learn":[0.3425514925],"iteration":943,"passed_time":7.10013538,"remaining_time":0.4211944717},
{"learn":[0.3424770519],"iteration":944,"passed_time":7.107520536,"remaining_time":0.4136652164},
{"learn":[0.3424053945],"iteration":945,"passed_time":7.113980629,"remaining_time":0.4060834608},
{"learn":[0.3423296312],"iteration":946,"passed_time":7.121370358,"remaining_time":0.3985561024},
{"learn":[0.3422612402],"iteration":947,"passed_time":7.127817124,"remaining_time":0.3909773106},
{"learn":[0.3421834332],"iteration":948,"passed_time":7.134495435,"remaining_time":0.3834133479},
{"learn":[0.3421198673],"iteration":949,"passed_time":7.141439507,"remaining_time":0.3758652372},
{"learn":[0.3420458473],"iteration":950,"passed_time":7.148132534,"remaining_time":0.3683054618},
{"learn":[0.3419984068],"iteration":951,"passed_time":7.155422509,"remaining_time":0.3607776055},
{"learn":[0.341929708],"iteration":952,"passed_time":7.162389672,"remaining_time":0.353234328},
{"learn":[0.3418647514],"iteration":953,"passed_time":7.169258738,"remaining_time":0.3456875282},
{"learn":[0.3418322602],"iteration":954,"passed_time":7.175887014,"remaining_time":0.3381308017},
{"learn":[0.3417595137],"iteration":955,"passed_time":7.182785827,"remaining_time":0.330588469},
{"learn":[0.3416719578],"iteration":956,"passed_time":7.190056657,"remaining_time":0.3230641967},
{"learn":[0.3416521761],"iteration":957,"passed_time":7.196435922,"remaining_time":0.3155013661},
{"learn":[0.3415631571],"iteration":958,"passed_time":7.203831051,"remaining_time":0.3079844349},
{"learn":[0.3415234519],"iteration":959,"passed_time":7.210658043,"remaining_time":0.3004440851},
{"learn":[0.341462554],"iteration":960,"passed_time":7.217328451,"remaining_time":0.2928988653},
{"learn":[0.3413967307],"iteration":961,"passed_time":7.223961489,"remaining_time":0.2853539882},
{"learn":[0.3412534697],"iteration":962,"passed_time":7.230675005,"remaining_time":0.2778140968},
{"learn":[0.3411743471],"iteration":963,"passed_time":7.237894563,"remaining_time":0.2702948177},
{"learn":[0.3410903593],"iteration":964,"passed_time":7.244648099,"remaining_time":0.2627592575},
{"learn":[0.3410150509],"iteration":965,"passed_time":7.25224962,"remaining_time":0.2552551626},
{"learn":[0.3409522158],"iteration":966,"passed_time":7.259671077,"remaining_time":0.2477447213},
{"learn":[0.3408431896],"iteration":967,"passed_time":7.267307384,"remaining_time":0.2402415664},
{"learn":[0.3407785232],"iteration":968,"passed_time":7.275439266,"remaining_time":0.232753991},
{"learn":[0.3407129569],"iteration":969,"passed_time":7.282185488,"remaining_time":0.2252222316},
{"learn":[0.3406079792],"iteration":970,"passed_time":7.289860733,"remaining_time":0.2177198365},
{"learn":[0.3405711001],"iteration":971,"passed_time":7.296540161,"remaining_time":0.2101883997},
{"learn":[0.3404929473],"iteration":972,"passed_time":7.303629401,"remaining_time":0.2026700862},
{"learn":[0.3404476533],"iteration":973,"passed_time":7.309865894,"remaining_time":0.1951298904},
{"learn":[0.3403845427],"iteration":974,"passed_time":7.317096122,"remaining_time":0.1876178493},
{"learn":[0.340294402],"iteration":975,"passed_time":7.343142492,"remaining_time":0.1805690777},
{"learn":[0.3402501584],"iteration":976,"passed_time":7.363181952,"remaining_time":0.173340005},
{"learn":[0.3402145756],"iteration":977,"passed_time":7.376492665,"remaining_time":0.1659333728},
{"learn":[0.3401471579],"iteration":978,"passed_time":7.386416393,"remaining_time":0.1584420268},
{"learn":[0.3401067331],"iteration":979,"passed_time":7.397574451,"remaining_time":0.1509709072},
{"learn":[0.3400685231],"iteration":980,"passed_time":7.40697486,"remaining_time":0.1434582287},
{"learn":[0.3400366687],"iteration":981,"passed_time":7.416758701,"remaining_time":0.1359487338},
{"learn":[0.3399961931],"iteration":982,"passed_time":7.425282317,"remaining_time":0.1284128173},
{"learn":[0.3399305651],"iteration":983,"passed_time":7.432692992,"remaining_time":0.1208567966},
{"learn":[0.3398564277],"iteration":984,"passed_time":7.441031508,"remaining_time":0.1133152006},
{"learn":[0.3397815304],"iteration":985,"passed_time":7.449042896,"remaining_time":0.1057673434},
{"learn":[0.3397379058],"iteration":986,"passed_time":7.458622375,"remaining_time":0.09823920048},
{"learn":[0.339691503],"iteration":987,"passed_time":7.465615279,"remaining_time":0.09067548922},
{"learn":[0.3396452736],"iteration":988,"passed_time":7.473795637,"remaining_time":0.08312613955},
{"learn":[0.3395823175],"iteration":989,"passed_time":7.481627492,"remaining_time":0.07557199487},
{"learn":[0.3394827733],"iteration":990,"passed_time":7.489810096,"remaining_time":0.06802047514},
{"learn":[0.3394226705],"iteration":991,"passed_time":7.497829097,"remaining_time":0.06046636369},
{"learn":[0.3393399387],"iteration":992,"passed_time":7.506011376,"remaining_time":0.0529124669},
{"learn":[0.3393030833],"iteration":993,"passed_time":7.514107132,"remaining_time":0.04535678349},
{"learn":[0.3392474345],"iteration":994,"passed_time":7.522762848,"remaining_time":0.03780282838},
{"learn":[0.339161992],"iteration":995,"passed_time":7.530187151,"remaining_time":0.03024171547},
{"learn":[0.3391161281],"iteration":996,"passed_time":7.538376574,"remaining_time":0.02268317926},
{"learn":[0.3390399682],"iteration":997,"passed_time":7.546497943,"remaining_time":0.01512324237},
{"learn":[0.3389617888],"iteration":998,"passed_time":7.555646626,"remaining_time":0.007563209836},
{"learn":[0.3388936343],"iteration":999,"passed_time":7.563083217,"remaining_time":0}
]}